{"error_code":0,"data":{"offset":520,"songlist":[{"audio_info":{"duration_128":146050,"hash_128":"6F61047B21B0EDC713EBF933F1BC8300","filesize_128":2337423},"audio_name":"A计划","author_name":"小蓝背心","privilege_play":{"privilege_128":8},"album_info":{"album_name":"A计划","album_id":56648226,"sizable_cover":"http:\/\/imge.kugou.com\/stdmusic\/{size}\/20220412\/20220412172032554144.jpg"},"album_audio_id":402903007},{"audio_info":{"duration_128":232542,"hash_128":"900D1F5E394C60CBAF75C112A221A2E3","filesize_128":3721310},"audio_name":"风雨人生路 (粤语版)","author_name":"亮声open","privilege_play":{"privilege_128":8},"album_info":{"album_name":"风雨人生路 (粤语版)","album_id":51000031,"sizable_cover":"http:\/\/imge.kugou.com\/stdmusic\/{size}\/20211208\/20211208173416539956.jpg"},"album_audio_id":356799540},{"audio_info":{"duration_128":253000,"hash_128":"6DBBD392A5C6134D34F4C59F90705E3F","filesize_128":4052724},"audio_name":"唐刀","author_name":"屿汐学长","privilege_play":{"privilege_128":8},"album_info":{"album_name":"唐刀","album_id":29972996,"sizable_cover":"http:\/\/imge.kugou.com\/stdmusic\/{size}\/20200103\/20200103221322127811.jpg"},"album_audio_id":218814293},{"audio_info":{"duration_128":188000,"hash_128":"99EB9D46B1BFA3D52366343E4300BE1B","filesize_128":3019953},"audio_name":"光的方向","author_name":"王雨桐","privilege_play":{"privilege_128":8},"album_info":{"album_name":"光的方向","album_id":46173509,"sizable_cover":"http:\/\/imge.kugou.com\/stdmusic\/{size}\/20210626\/20210626185256546063.jpg"},"album_audio_id":324463674},{"audio_info":{"duration_128":206576,"hash_128":"DA8FC86D724AECB41268DFF12ECA3509","filesize_128":3305869},"audio_name":"荒变","author_name":"醉雪","privilege_play":{"privilege_128":8},"album_info":{"album_name":"武动乾坤 动画第三季原声带","album_id":57105711,"sizable_cover":"http:\/\/imge.kugou.com\/stdmusic\/{size}\/20220429\/20220429204602828667.jpg"},"album_audio_id":408000262},{"audio_info":{"duration_128":240039,"hash_128":"29FA8347F827BE8697A268854B808ECE","filesize_128":3841232},"audio_name":"作者","author_name":"高源","privilege_play":{"privilege_128":8},"album_info":{"album_name":"作者","album_id":40299755,"sizable_cover":"http:\/\/imge.kugou.com\/stdmusic\/{size}\/20201125\/20201125114902428787.jpg"},"album_audio_id":282843184},{"audio_info":{"duration_128":164000,"hash_128":"346B64CFF3252507150CA2E67F997940","filesize_128":2625413},"audio_name":"别挡着我喝西北风","author_name":"许先","privilege_play":{"privilege_128":8},"album_info":{"album_name":"别挡着我喝西北风","album_id":38220483,"sizable_cover":"http:\/\/imge.kugou.com\/stdmusic\/{size}\/20200623\/20200623145503619116.jpg"},"album_audio_id":262370335},{"audio_info":{"duration_128":193000,"hash_128":"85FA4ADD42675AAB83EF297EC562A3E2","filesize_128":3096021},"audio_name":"人间种种","author_name":"戴羽彤","privilege_play":{"privilege_128":8},"album_info":{"album_name":"人间种种","album_id":49744308,"sizable_cover":"http:\/\/imge.kugou.com\/stdmusic\/{size}\/20211022\/20211022141456267491.jpg"},"album_audio_id":344424799},{"audio_info":{"duration_128":207124,"hash_128":"84E126C8BDB4506A702D8D422F652680","filesize_128":3314659},"audio_name":"逆流而上","author_name":"梦然","privilege_play":{"privilege_128":8},"album_info":{"album_name":"逆流而上","album_id":57100755,"sizable_cover":"http:\/\/imge.kugou.com\/stdmusic\/{size}\/20220429\/20220429161402252353.jpg"},"album_audio_id":407949940},{"audio_info":{"duration_128":258000,"hash_128":"15D376CAAF40DBF85C4169C3EEB9E753","filesize_128":4132980},"audio_name":"懦弱","author_name":"于黑蛋","privilege_play":{"privilege_128":8},"album_info":{"album_name":"懦弱","album_id":35524047,"sizable_cover":"http:\/\/imge.kugou.com\/stdmusic\/{size}\/20191230\/20191230185215768138.jpg"},"album_audio_id":245515885},{"audio_info":{"duration_128":208000,"hash_128":"4860E25CCABD46E2838324A678C35C4F","filesize_128":3330492},"audio_name":"少无忧","author_name":"饭思思","privilege_play":{"privilege_128":8},"album_info":{"album_name":"少无忧","album_id":39554827,"sizable_cover":"http:\/\/imge.kugou.com\/stdmusic\/{size}\/20201013\/20201013140612463973.jpg"},"album_audio_id":276955153},{"audio_info":{"duration_128":250000,"hash_128":"AD13296792029096B58DBCC331DBC00A","filesize_128":4010528},"audio_name":"开心过好每一天","author_name":"王木泉","privilege_play":{"privilege_128":0},"album_info":{"album_name":"开心过好每一天","album_id":43411952,"sizable_cover":"http:\/\/imge.kugou.com\/stdmusic\/{size}\/20210408\/20210408171502587339.jpg"},"album_audio_id":307496373},{"audio_info":{"duration_128":243000,"hash_128":"BEF5663D597A101D7E85832A7922F5AB","filesize_128":3892497},"audio_name":"姐就是姐","author_name":"轻云望月","privilege_play":{"privilege_128":8},"album_info":{"album_name":"姐就是姐","album_id":49187527,"sizable_cover":"http:\/\/imge.kugou.com\/stdmusic\/{size}\/20210929\/20210929135418618091.jpg"},"album_audio_id":340310708},{"audio_info":{"duration_128":218000,"hash_128":"3A23DE77CCACE6D2009177C4D243A5E6","filesize_128":3490585},"audio_name":"微笑吧 (烟嗓版)","author_name":"烟嗓大叔","privilege_play":{"privilege_128":8},"album_info":{"album_name":"微笑吧 (烟嗓版)","album_id":37903674,"sizable_cover":"http:\/\/imge.kugou.com\/stdmusic\/{size}\/20200603\/20200603202113497682.jpg"},"album_audio_id":253001999},{"audio_info":{"duration_128":219000,"hash_128":"77432C7C5A02606A2B5B8369011A9AE1","filesize_128":3506041},"audio_name":"巳时","author_name":"李佳思","privilege_play":{"privilege_128":8},"album_info":{"album_name":"十二时辰","album_id":48381939,"sizable_cover":"http:\/\/imge.kugou.com\/stdmusic\/{size}\/20210827\/20210827170704753730.jpg"},"album_audio_id":333989486},{"audio_info":{"duration_128":186201,"hash_128":"D6FC5F97BEB9F9E0ECED6F25EC6ECC82","filesize_128":2979725},"audio_name":"怎么开心就怎么来","author_name":"杨顺高","privilege_play":{"privilege_128":8},"album_info":{"album_name":"怎么开心就怎么来","album_id":52019236,"sizable_cover":"http:\/\/imge.kugou.com\/stdmusic\/{size}\/20220102\/20220102194525135384.jpg"},"album_audio_id":364493757},{"audio_info":{"duration_128":277000,"hash_128":"801B45BFFD7F76DE6C000B560125D43C","filesize_128":4433042},"audio_name":"生活","author_name":"郭旺","privilege_play":{"privilege_128":8},"album_info":{"album_name":"生活-郭旺","album_id":50382078,"sizable_cover":"http:\/\/imge.kugou.com\/stdmusic\/{size}\/20211113\/20211113141808514621.jpg"},"album_audio_id":349597890},{"audio_info":{"duration_128":178128,"hash_128":"0CE6B0F99707DF546503CE9475EB1231","filesize_128":2850679},"audio_name":"妈妈的话","author_name":"李飘飘","privilege_play":{"privilege_128":8},"album_info":{"album_name":"妈妈的话","album_id":56180456,"sizable_cover":"http:\/\/imge.kugou.com\/stdmusic\/{size}\/20220330\/20220330115310106418.jpg"},"album_audio_id":393401485},{"audio_info":{"duration_128":243000,"hash_128":"676F450738644018A91CFE2F5DFA1286","filesize_128":3900558},"audio_name":"到了这个年纪 (新版)","author_name":"赵阿光","privilege_play":{"privilege_128":8},"album_info":{"album_name":"到了这个年纪(新版)","album_id":44984332,"sizable_cover":"http:\/\/imge.kugou.com\/stdmusic\/{size}\/20210526\/20210526151102325779.jpg"},"album_audio_id":315779067},{"audio_info":{"duration_128":216000,"hash_128":"A7786E2DFBBFA191CE34B6CDC1AB9477","filesize_128":3465049},"audio_name":"多少回忆度春秋","author_name":"关剑","privilege_play":{"privilege_128":8},"album_info":{"album_name":"多少回忆度春秋","album_id":47062858,"sizable_cover":"http:\/\/imge.kugou.com\/stdmusic\/{size}\/20210722\/20210722152817567825.jpg"},"album_audio_id":328461152}]},"status":1}
