{"error_code":0,"data":{"offset":460,"songlist":[{"audio_info":{"duration_128":208000,"hash_128":"70843F3A72B96EA4B24C165CEBF59CF3","filesize_128":3332584},"audio_name":"想你了","author_name":"鞠婧祎","privilege_play":{"privilege_128":0},"album_info":{"album_name":"等不到你","album_id":2679067,"sizable_cover":"http:\/\/imge.kugou.com\/stdmusic\/{size}\/20170526\/20170526104306329906.jpg"},"album_audio_id":66025828},{"audio_info":{"duration_128":251000,"hash_128":"5CF0DFBA09A091B50EBCB840F0485B20","filesize_128":4020961},"audio_name":"因为你","author_name":"庄心妍","privilege_play":{"privilege_128":8},"album_info":{"album_name":"因为你","album_id":39650985,"sizable_cover":"http:\/\/imge.kugou.com\/stdmusic\/{size}\/20200929\/20200929154907515570.jpg"},"album_audio_id":275847568},{"audio_info":{"duration_128":168000,"hash_128":"CA89D70474D82CFE5AAFB3918430DBB7","filesize_128":2689379},"audio_name":"Space","author_name":"Toito、Karli、Famba","privilege_play":{"privilege_128":8},"album_info":{"album_name":"Space","album_id":3045808,"sizable_cover":"http:\/\/imge.kugou.com\/stdmusic\/{size}\/20170822\/20170822001218620707.jpg"},"album_audio_id":68870900},{"audio_info":{"duration_128":192000,"hash_128":"0C7B812BFE65694F5D584B1D9946EF9E","filesize_128":3075167},"audio_name":"Tired","author_name":"Gavin James、Alan Walker","privilege_play":{"privilege_128":8},"album_info":{"album_name":"Tired","album_id":2654300,"sizable_cover":"http:\/\/imge.kugou.com\/stdmusic\/{size}\/20200909\/20200909123822181110.jpg"},"album_audio_id":65170922},{"audio_info":{"duration_128":201064,"hash_128":"42BA139E543D76A9E389FF496EED0FAB","filesize_128":3217637},"audio_name":"我们","author_name":"萨吉","privilege_play":{"privilege_128":8},"album_info":{"album_name":"沉睡花园 影视原声带","album_id":51608416,"sizable_cover":"http:\/\/imge.kugou.com\/stdmusic\/{size}\/20211221\/20211221171006935319.jpg"},"album_audio_id":358577527},{"audio_info":{"duration_128":144000,"hash_128":"68598B1E17C6319590E6AF8D34BF70E0","filesize_128":2319893},"audio_name":"honeysea","author_name":"Ivorish","privilege_play":{"privilege_128":8},"album_info":{"album_name":"honeysea","album_id":20285965,"sizable_cover":"http:\/\/imge.kugou.com\/stdmusic\/{size}\/20210715\/20210715105401983124.jpg"},"album_audio_id":151721830},{"audio_info":{"duration_128":210000,"hash_128":"03893017100E8A81A2D20A5DF7F96DAB","filesize_128":3376064},"audio_name":"花房咖啡厅","author_name":"杨紫、吴牧野","privilege_play":{"privilege_128":8},"album_info":{"album_name":"女心理师 电视剧原声带","album_id":50754862,"sizable_cover":"http:\/\/imge.kugou.com\/stdmusic\/{size}\/20211126\/20211126215204695851.jpg"},"album_audio_id":353992343},{"audio_info":{"duration_128":211000,"hash_128":"862F8E232478314283DEFFDEE4AE6F3E","filesize_128":3381957},"audio_name":"This Side Of You","author_name":"Rick Monroe","privilege_play":{"privilege_128":8},"album_info":{"album_name":"Gypsy Soul","album_id":8421031,"sizable_cover":"http:\/\/imge.kugou.com\/stdmusic\/{size}\/20180315\/20180315152138154022.jpg"},"album_audio_id":106670656},{"audio_info":{"duration_128":248000,"hash_128":"85D83BD44040E7C8784EC13DEC81EE93","filesize_128":3971226},"audio_name":"我想","author_name":"余佳运","privilege_play":{"privilege_128":8},"album_info":{"album_name":"幸福三部曲","album_id":1987128,"sizable_cover":"http:\/\/imge.kugou.com\/stdmusic\/{size}\/20170308\/20170308084007369244.jpg"},"album_audio_id":54344009},{"audio_info":{"duration_128":274000,"hash_128":"00EE40A3CF2F4E5EE1063141ED67A4C8","filesize_128":4385431},"audio_name":"真心真意过一生","author_name":"韩宝仪","privilege_play":{"privilege_128":8},"album_info":{"album_name":"一世情缘","album_id":8016764,"sizable_cover":"http:\/\/imge.kugou.com\/stdmusic\/{size}\/20210112\/20210112210451864115.jpg"},"album_audio_id":103817019},{"audio_info":{"duration_128":246000,"hash_128":"3C704F8A938F5DC230BEC22333462FDE","filesize_128":3949168},"audio_name":"Fire On Fire","author_name":"Sam Smith","privilege_play":{"privilege_128":8},"album_info":{"album_name":"Fire On Fire","album_id":13910171,"sizable_cover":"http:\/\/imge.kugou.com\/stdmusic\/{size}\/20181221\/20181221111149469207.jpg"},"album_audio_id":126003580},{"audio_info":{"duration_128":228000,"hash_128":"30CEF9BB8EB2D78D88C6F4A0D68F368C","filesize_128":3653177},"audio_name":"走着走着花就开了","author_name":"卓舒晨","privilege_play":{"privilege_128":8},"album_info":{"album_name":"走着走着花就开了","album_id":13752955,"sizable_cover":"http:\/\/imge.kugou.com\/stdmusic\/{size}\/20200103\/20200103191113670052.jpg"},"album_audio_id":125415781},{"audio_info":{"duration_128":310000,"hash_128":"4D5C5FDFB1B5A0AC7CE20B614FCFFC21","filesize_128":4969326},"audio_name":"北极星","author_name":"罗志祥、May J.","privilege_play":{"privilege_128":8},"album_info":{"album_name":"真人秀？","album_id":557182,"sizable_cover":"http:\/\/imge.kugou.com\/stdmusic\/{size}\/20210816\/20210816092905883970.jpg"},"album_audio_id":62273944},{"audio_info":{"duration_128":217000,"hash_128":"B9BCF451227BBF5A8CB2E0E89FC900F7","filesize_128":3484735},"audio_name":"小酒窝 (独唱版)","author_name":"林俊杰","privilege_play":{"privilege_128":8},"album_info":{"album_name":"他是... JJ林俊杰","album_id":1740482,"sizable_cover":"http:\/\/imge.kugou.com\/stdmusic\/{size}\/20160907\/20160907183615552268.jpg"},"album_audio_id":39608713},{"audio_info":{"duration_128":280000,"hash_128":"8015344E6A43BF9F20CC4E57CAA47B19","filesize_128":4482814},"audio_name":"下世纪初雪","author_name":"朱星杰","privilege_play":{"privilege_128":8},"album_info":{"album_name":"下世纪初雪","album_id":37114037,"sizable_cover":"http:\/\/imge.kugou.com\/stdmusic\/{size}\/20200417\/20200417083445501598.jpg"},"album_audio_id":253842737},{"audio_info":{"duration_128":249000,"hash_128":"1CDC1532FF6F3E43B680E294BA3BE5B7","filesize_128":3995053},"audio_name":"秘语","author_name":"欧阳娜娜、陈飞宇","privilege_play":{"privilege_128":8},"album_info":{"album_name":"秘语","album_id":2710068,"sizable_cover":"http:\/\/imge.kugou.com\/stdmusic\/{size}\/20210820\/20210820152801327323.jpg"},"album_audio_id":66028583},{"audio_info":{"duration_128":303000,"hash_128":"60E32E443275A886CC0FAA91A89928BB","filesize_128":4864027},"audio_name":"Beautiful Love","author_name":"毕夏","privilege_play":{"privilege_128":8},"album_info":{"album_name":"我的青春高八度 电视剧原声带","album_id":537999,"sizable_cover":"http:\/\/imge.kugou.com\/stdmusic\/{size}\/20200909\/20200909115449519310.jpg"},"album_audio_id":27715297},{"audio_info":{"duration_128":213000,"hash_128":"8E1031E76947D5B35074069887B861B9","filesize_128":3409087},"audio_name":"Honey","author_name":"王心凌","privilege_play":{"privilege_128":8},"album_info":{"album_name":"My! Cyndi!","album_id":39026197,"sizable_cover":"http:\/\/imge.kugou.com\/stdmusic\/{size}\/20200827\/20200827171305512052.jpg"},"album_audio_id":272175214},{"audio_info":{"duration_128":255686,"hash_128":"3CE88D43AB4AE6A910D627CB137492C6","filesize_128":4091630},"audio_name":"幸福的样子","author_name":"林佑威、赵樱子","privilege_play":{"privilege_128":8},"album_info":{"album_name":"因为爱情有奇迹 电视剧原声带","album_id":541372,"sizable_cover":"http:\/\/imge.kugou.com\/stdmusic\/{size}\/20200909\/20200909120015171394.jpg"},"album_audio_id":27753097}]},"status":1}
