{"status":1,"error_code":0,"data":[{"offset":460,"size":20,"fmid":1308,"fmtype":2,"songs":[{"filesize_high":0,"hash_ape":"","pay_type_320":0,"hashflac":"A519B0D12E98F52EA2E1E6CAE201350E","tracker_info":{},"topic_url":"","type_320":"","pkg_price_320":0,"sid":374055943,"topic_remark":"","filesize_ape":0,"bitrate":128,"isfilehead":100,"time":"196310","name":"汪晨蕊 - 入长空","pkg_price_flac":0,"pay_type_flac":0,"320isfilehead":100,"hash_super":"","hash_high":"","fail_process_flac":0,"fail_process_320":0,"pay_type":3,"pkg_price_128":0,"album_id":"53390377","publish":1,"filesize_flac":21590079,"ext":"mp3","scid":145526176,"m4ahash":"","privilege_128":0,"_is_recommend":0,"privilege_flac":0,"price_320":0,"trac":"","mvtype":0,"privilege_320":0,"pay_type_128":0,"mvhash":"","trans_param":{"cpy_grade":5,"musicpack_advance":0,"cpy_level":1,"cid":195145292,"hash_multitrack":"F349DE5B41C42F26EAEB126633751530","pay_block_tpl":1,"classmap":{"attr0":100663304},"display_rate":0,"appid_block":"3124","display":0,"cpy_attr0":0},"privilege":8,"price_flac":0,"mv":"","album_audio_id":374055943,"all_privs":{"4":{"status":0,"privilege":8,"fail_process":4},"6":{"status":0,"privilege":8,"fail_process":4},"3":{"status":0,"privilege":8,"fail_process":4},"5":{"status":0,"privilege":8,"fail_process":4}},"vip":0,"type_flac":"","price_128":0,"hmvhash":"","hash":"4A7F16F548ECF01B2567E6B82C09940E","size":"3141575","ismvfilehead":0,"filesize_super":0,"musictrac":0,"old_cpy":0,"fail_process":4,"320size":"7853647","320time":"196310","fail_process_128":0,"320hash":"3C9E6183CA8990C89A26BB00D9FD241C","type":"audio","audio_id":145526176,"m4asize":0,"type_128":""},{"filesize_high":0,"hash_ape":"","pay_type_320":0,"hashflac":"2C21E6F8B8C145954C139B403E30B8A8","tracker_info":{},"topic_url":"","type_320":"","pkg_price_320":0,"sid":334947294,"topic_remark":"","filesize_ape":0,"bitrate":128,"isfilehead":100,"time":"233000","name":"刘瑞琦 - 两三句","pkg_price_flac":0,"pay_type_flac":0,"320isfilehead":100,"hash_super":"","hash_high":"","fail_process_flac":0,"fail_process_320":0,"pay_type":3,"pkg_price_128":0,"album_id":"48516816","publish":1,"filesize_flac":25822513,"ext":"mp3","scid":118915332,"m4ahash":"","privilege_128":0,"_is_recommend":0,"privilege_flac":0,"price_320":0,"trac":"","mvtype":0,"privilege_320":0,"pay_type_128":0,"mvhash":"","trans_param":{"cpy_grade":5,"cpy_attr0":0,"cpy_level":1,"cid":167294600,"hash_multitrack":"C619D66C5B79D8B1913E4A7FFFD03888","pay_block_tpl":1,"display_rate":1,"classmap":{"attr0":100667400},"display":32,"musicpack_advance":0},"privilege":8,"price_flac":0,"mv":"","album_audio_id":334947294,"all_privs":{"4":{"status":0,"privilege":5,"fail_process":0},"6":{"privilege":10,"status":0,"trans_param":{"cpy_grade":5,"musicpack_advance":0,"cpy_level":1,"identity_block":1,"pay_block_tpl":1,"cpy_attr0":0,"display_rate":1,"classmap":{"attr0":100667400},"display":32,"cid":167294600},"pay_type":1,"fail_process":4},"3":{"status":0,"privilege":5,"fail_process":0},"5":{"privilege":10,"status":0,"trans_param":{"cpy_grade":5,"musicpack_advance":0,"cpy_level":1,"identity_block":1,"pay_block_tpl":1,"cpy_attr0":0,"display_rate":1,"classmap":{"attr0":100667400},"display":32,"cid":167294600},"pay_type":1,"fail_process":4}},"vip":0,"type_flac":"","price_128":0,"hmvhash":"","hash":"6FE3BDBDBE58DF2DAB96F573B92EFB26","size":"3731733","ismvfilehead":0,"filesize_super":0,"musictrac":0,"old_cpy":0,"fail_process":4,"320size":"9328600","320time":"233000","fail_process_128":0,"320hash":"A1A4A9CB67A38FE12E8789BE94D30EAE","type":"audio","audio_id":118915332,"m4asize":0,"type_128":""},{"filesize_high":0,"hash_ape":"","pay_type_320":0,"hashflac":"89930747F7C10A476E059395493A29E5","tracker_info":{},"topic_url":"","type_320":"","pkg_price_320":0,"sid":147490776,"topic_remark":"","filesize_ape":0,"bitrate":128,"isfilehead":100,"time":"212767","name":"任然 - 花雨落","pkg_price_flac":0,"pay_type_flac":0,"320isfilehead":100,"hash_super":"","hash_high":"","fail_process_flac":0,"fail_process_320":0,"pay_type":3,"pkg_price_128":0,"album_id":"19461959","publish":1,"filesize_flac":21091241,"ext":"mp3","scid":54130591,"m4ahash":"","privilege_128":0,"_is_recommend":0,"privilege_flac":0,"price_320":0,"trac":"","mvtype":0,"privilege_320":0,"pay_type_128":0,"mvhash":"","trans_param":{"cpy_grade":5,"cpy_attr0":0,"cpy_level":1,"cid":69141713,"hash_multitrack":"AFBD1346B851F61E17B7F0065FBFE8F6","pay_block_tpl":1,"display_rate":0,"classmap":{"attr0":100663304},"display":0,"musicpack_advance":0},"privilege":8,"price_flac":0,"mv":"","album_audio_id":147490776,"all_privs":{"4":{"status":0,"privilege":8,"fail_process":4},"6":{"status":0,"privilege":8,"fail_process":4},"3":{"status":0,"privilege":8,"fail_process":4},"5":{"status":0,"privilege":8,"fail_process":4}},"vip":0,"type_flac":"","price_128":0,"hmvhash":"","hash":"0E80F4FC65AF682E51806D9BA71528E7","size":"3404739","ismvfilehead":0,"filesize_super":0,"musictrac":0,"old_cpy":0,"fail_process":4,"320size":"8511782","320time":"212767","fail_process_128":0,"320hash":"4EDDC3D50B1E3DA1D9EBB73580513D96","type":"audio","audio_id":54130591,"m4asize":0,"type_128":""},{"filesize_high":0,"hash_ape":"","pay_type_320":0,"hashflac":"D206C171EDE926697EE8481BAB55C197","tracker_info":{},"topic_url":"","type_320":"","pkg_price_320":0,"sid":125282603,"topic_remark":"","filesize_ape":0,"bitrate":128,"isfilehead":100,"time":"247000","name":"苏运莹 - 时候","pkg_price_flac":0,"pay_type_flac":0,"320isfilehead":100,"hash_super":"","hash_high":"","fail_process_flac":0,"fail_process_320":0,"pay_type":3,"pkg_price_128":0,"album_id":"13669576","publish":1,"filesize_flac":27004835,"ext":"mp3","scid":47802302,"m4ahash":"","privilege_128":0,"_is_recommend":0,"privilege_flac":0,"price_320":0,"trac":"","mvtype":0,"privilege_320":0,"pay_type_128":0,"mvhash":"","trans_param":{"cpy_grade":5,"cpy_attr0":0,"cpy_level":1,"cid":53697364,"hash_multitrack":"3A9B3B68C7B63B1E41817E697063AB38","pay_block_tpl":1,"display_rate":1,"classmap":{"attr0":100667400},"display":32,"musicpack_advance":0},"privilege":8,"price_flac":0,"mv":"","album_audio_id":125282603,"all_privs":{"4":{"privilege":10,"status":0,"trans_param":{"cpy_grade":5,"musicpack_advance":0,"cpy_level":1,"identity_block":1,"pay_block_tpl":1,"cpy_attr0":0,"display_rate":1,"classmap":{"attr0":100667400},"display":32,"cid":53697364},"pay_type":5,"fail_process":4},"6":{"privilege":10,"status":0,"trans_param":{"cpy_grade":5,"musicpack_advance":0,"cpy_level":1,"identity_block":1,"pay_block_tpl":1,"cpy_attr0":0,"display_rate":1,"classmap":{"attr0":100667400},"display":32,"cid":53697364},"pay_type":5,"fail_process":4},"3":{"status":0,"privilege":5,"fail_process":0},"5":{"privilege":10,"status":0,"trans_param":{"cpy_grade":5,"musicpack_advance":0,"cpy_level":1,"identity_block":1,"pay_block_tpl":1,"cpy_attr0":0,"display_rate":1,"classmap":{"attr0":100667400},"display":32,"cid":53697364},"pay_type":5,"fail_process":4}},"vip":0,"type_flac":"","price_128":0,"hmvhash":"","hash":"41D8878D6FCE2973B036E561F11617EF","size":"3955335","ismvfilehead":0,"filesize_super":0,"musictrac":0,"old_cpy":0,"fail_process":4,"320size":"9888057","320time":"247000","fail_process_128":0,"320hash":"6AF023D9C5A76A541E2D5EE265D4B368","type":"audio","audio_id":47802302,"m4asize":0,"type_128":""},{"filesize_high":0,"hash_ape":"","pay_type_320":0,"hashflac":"D4CF2B822FAA3D3CBBEE96B9D3348507","tracker_info":{},"topic_url":"","type_320":"","pkg_price_320":0,"sid":330482570,"topic_remark":"","filesize_ape":0,"bitrate":128,"isfilehead":100,"time":"249000","name":"黄霄雲 - 带我去很远地方","pkg_price_flac":0,"pay_type_flac":0,"320isfilehead":100,"hash_super":"","hash_high":"","fail_process_flac":0,"fail_process_320":0,"pay_type":3,"pkg_price_128":0,"album_id":"47601928","publish":1,"filesize_flac":28895543,"ext":"mp3","scid":115816689,"m4ahash":"","privilege_128":0,"_is_recommend":0,"privilege_flac":0,"price_320":0,"trac":"","mvtype":0,"privilege_320":0,"pay_type_128":0,"mvhash":"","trans_param":{"cpy_grade":5,"musicpack_advance":0,"cpy_level":1,"cid":163655384,"hash_multitrack":"8FE952FAEDC8BD00394B5DF5D2997E69","pay_block_tpl":1,"classmap":{"attr0":100663304},"display_rate":0,"appid_block":"3124","display":0,"cpy_attr0":0},"privilege":8,"price_flac":0,"mv":"","album_audio_id":330482570,"all_privs":{"4":{"status":0,"privilege":5,"fail_process":0},"6":{"privilege":10,"status":0,"trans_param":{"cpy_grade":5,"cpy_attr0":0,"cpy_level":1,"identity_block":1,"musicpack_advance":0,"pay_block_tpl":1,"classmap":{"attr0":100663304},"display_rate":0,"appid_block":"3124","display":0,"cid":163655384},"pay_type":1,"fail_process":4},"3":{"status":0,"privilege":5,"fail_process":0},"5":{"privilege":10,"status":0,"trans_param":{"cpy_grade":5,"cpy_attr0":0,"cpy_level":1,"identity_block":1,"musicpack_advance":0,"pay_block_tpl":1,"classmap":{"attr0":100663304},"display_rate":0,"appid_block":"3124","display":0,"cid":163655384},"pay_type":1,"fail_process":4}},"vip":0,"type_flac":"","price_128":0,"hmvhash":"","hash":"ED0AD6F48E50E619376277764B30FA3C","size":"3987540","ismvfilehead":0,"filesize_super":0,"musictrac":0,"old_cpy":0,"fail_process":4,"320size":"9968536","320time":"249000","fail_process_128":0,"320hash":"200D0EAFF1D63C6FD3023E27B9F133F8","type":"audio","audio_id":115816689,"m4asize":0,"type_128":""},{"filesize_high":0,"hash_ape":"","pay_type_320":0,"hashflac":"A0EB5FE8F2BB631D05D63F4DA9263147","tracker_info":{},"topic_url":"","type_320":"","pkg_price_320":0,"sid":129258565,"topic_remark":"","filesize_ape":0,"bitrate":128,"isfilehead":100,"time":"170000","name":"HeRo.H、小咪 - 即兴 (说唱版)","pkg_price_flac":0,"pay_type_flac":0,"320isfilehead":100,"hash_super":"","hash_high":"","fail_process_flac":0,"fail_process_320":0,"pay_type":3,"pkg_price_128":0,"album_id":"14650948","publish":1,"filesize_flac":20759374,"ext":"mp3","scid":49541004,"m4ahash":"","privilege_128":0,"_is_recommend":0,"privilege_flac":0,"price_320":0,"trac":"","mvtype":0,"privilege_320":0,"pay_type_128":0,"mvhash":"","trans_param":{"cpy_grade":5,"cpy_attr0":0,"cpy_level":1,"cid":57322397,"hash_multitrack":"62DE3CA39D03D2E706799492DFB3DA62","pay_block_tpl":1,"display_rate":0,"classmap":{"attr0":100663304},"display":0,"musicpack_advance":0},"privilege":8,"price_flac":0,"mv":"","album_audio_id":129258565,"all_privs":{"4":{"status":0,"privilege":5,"fail_process":0},"6":{"privilege":10,"status":0,"trans_param":{"cpy_grade":5,"musicpack_advance":0,"cpy_level":1,"identity_block":1,"pay_block_tpl":1,"cpy_attr0":0,"display_rate":0,"classmap":{"attr0":100663304},"display":0,"cid":57322397},"pay_type":1,"fail_process":4},"3":{"status":0,"privilege":5,"fail_process":0},"5":{"privilege":10,"status":0,"trans_param":{"cpy_grade":5,"musicpack_advance":0,"cpy_level":1,"identity_block":1,"pay_block_tpl":1,"cpy_attr0":0,"display_rate":0,"classmap":{"attr0":100663304},"display":0,"cid":57322397},"pay_type":1,"fail_process":4}},"vip":0,"type_flac":"","price_128":0,"hmvhash":"","hash":"E64B88815E76DFA93B37E3BBB0D15378","size":"2721962","ismvfilehead":0,"filesize_super":0,"musictrac":0,"old_cpy":0,"fail_process":4,"320size":"6804587","320time":"170000","fail_process_128":0,"320hash":"072F23D931F5CD7324C45E42A0ABCCBD","type":"audio","audio_id":49541004,"m4asize":0,"type_128":""},{"filesize_high":0,"hash_ape":"","pay_type_320":0,"hashflac":"BA612A9C26E28BBAA35AE2F5C116F1C4","tracker_info":{},"topic_url":"","type_320":"","pkg_price_320":0,"sid":225015478,"topic_remark":"","filesize_ape":0,"bitrate":128,"isfilehead":100,"time":"184000","name":"空匪 - Darling","pkg_price_flac":0,"pay_type_flac":0,"320isfilehead":100,"hash_super":"","hash_high":"","fail_process_flac":0,"fail_process_320":0,"pay_type":3,"pkg_price_128":0,"album_id":"31482654","publish":1,"filesize_flac":21176235,"ext":"mp3","scid":55438693,"m4ahash":"","privilege_128":0,"_is_recommend":0,"privilege_flac":0,"price_320":0,"trac":"","mvtype":0,"privilege_320":0,"pay_type_128":0,"mvhash":"","trans_param":{"cpy_grade":5,"musicpack_advance":0,"cpy_level":1,"cid":78528514,"hash_multitrack":"EE6966415238D7C45C44A184E8B5E51C","pay_block_tpl":1,"classmap":{"attr0":100663304},"display_rate":0,"appid_block":"3124","display":0,"cpy_attr0":0},"privilege":8,"price_flac":0,"mv":"","album_audio_id":225015478,"all_privs":{"4":{"status":0,"privilege":5,"fail_process":0},"6":{"privilege":10,"status":0,"trans_param":{"cpy_grade":5,"cpy_attr0":0,"cpy_level":1,"identity_block":1,"musicpack_advance":0,"pay_block_tpl":1,"classmap":{"attr0":100663304},"display_rate":0,"appid_block":"3124","display":0,"cid":78528514},"pay_type":1,"fail_process":4},"3":{"status":0,"privilege":5,"fail_process":0},"5":{"privilege":10,"status":0,"trans_param":{"cpy_grade":5,"cpy_attr0":0,"cpy_level":1,"identity_block":1,"musicpack_advance":0,"pay_block_tpl":1,"classmap":{"attr0":100663304},"display_rate":0,"appid_block":"3124","display":0,"cid":78528514},"pay_type":1,"fail_process":4}},"vip":0,"type_flac":"","price_128":0,"hmvhash":"","hash":"2BFE915D203EFEEDF5D26D4D64A804A1","size":"2950163","ismvfilehead":0,"filesize_super":0,"musictrac":0,"old_cpy":0,"fail_process":4,"320size":"7374408","320time":"184000","fail_process_128":0,"320hash":"AD9C36E797B30309063FA445E6B39DAC","type":"audio","audio_id":55438693,"m4asize":0,"type_128":""},{"filesize_high":0,"hash_ape":"","pay_type_320":0,"hashflac":"C75A6E2585050366FD0E7C31A0967B26","tracker_info":{},"topic_url":"","type_320":"","pkg_price_320":0,"sid":174800108,"topic_remark":"","filesize_ape":0,"bitrate":128,"isfilehead":100,"time":"222000","name":"习谱予、文颖秋 - Let Me Know","pkg_price_flac":0,"pay_type_flac":0,"320isfilehead":100,"hash_super":"","hash_high":"","fail_process_flac":0,"fail_process_320":0,"pay_type":0,"pkg_price_128":0,"album_id":"25310203","publish":1,"filesize_flac":27210841,"ext":"mp3","scid":27540743,"m4ahash":"","privilege_128":0,"_is_recommend":0,"privilege_flac":0,"price_320":0,"trac":"","mvtype":0,"privilege_320":0,"pay_type_128":0,"mvhash":"","trans_param":{"cpy_grade":5,"cpy_attr0":0,"cpy_level":1,"cid":73334438,"hash_multitrack":"D8CE6400D9029C00F01698AFD3AE9722","pay_block_tpl":1,"display_rate":0,"classmap":{"attr0":100663304},"display":0,"musicpack_advance":0},"privilege":0,"price_flac":0,"mv":"","album_audio_id":174800108,"all_privs":{"4":{"status":0,"privilege":5,"fail_process":0},"6":{"privilege":10,"status":0,"trans_param":{"cpy_grade":5,"musicpack_advance":0,"cpy_level":1,"identity_block":1,"pay_block_tpl":1,"cpy_attr0":0,"display_rate":0,"classmap":{"attr0":100663304},"display":0,"cid":73334438},"pay_type":1,"fail_process":4},"3":{"status":0,"privilege":5,"fail_process":0},"5":{"privilege":10,"status":0,"trans_param":{"cpy_grade":5,"musicpack_advance":0,"cpy_level":1,"identity_block":1,"pay_block_tpl":1,"cpy_attr0":0,"display_rate":0,"classmap":{"attr0":100663304},"display":0,"cid":73334438},"pay_type":1,"fail_process":4}},"vip":0,"type_flac":"","price_128":0,"hmvhash":"","hash":"CF306CAE0003C35444FDDC582E50D260","size":"3546593","ismvfilehead":0,"filesize_super":0,"musictrac":0,"old_cpy":1,"fail_process":0,"320size":"8866169","320time":"222000","fail_process_128":0,"320hash":"56C3A92D808FAA9E95A77EE766D94DD7","type":"audio","audio_id":27540743,"m4asize":0,"type_128":""},{"filesize_high":0,"hash_ape":"","pay_type_320":0,"hashflac":"","tracker_info":{},"topic_url":"","type_320":"","pkg_price_320":0,"sid":341673946,"topic_remark":"","filesize_ape":0,"bitrate":128,"isfilehead":100,"time":"152000","name":"yihuik苡慧 - 都不懂","pkg_price_flac":0,"pay_type_flac":0,"320isfilehead":100,"hash_super":"","hash_high":"","fail_process_flac":0,"fail_process_320":0,"pay_type":3,"pkg_price_128":0,"album_id":"49394348","publish":1,"filesize_flac":0,"ext":"mp3","scid":122996979,"m4ahash":"","privilege_128":0,"_is_recommend":0,"privilege_flac":0,"price_320":0,"trac":"","mvtype":0,"privilege_320":0,"pay_type_128":0,"mvhash":"","trans_param":{"cpy_grade":5,"cpy_attr0":0,"cpy_level":1,"cid":173413671,"hash_multitrack":"83CD57912E33D59EBD1B0EDC44DE0F23","pay_block_tpl":1,"display_rate":3,"classmap":{"attr0":100859912},"display":8,"musicpack_advance":0},"privilege":8,"price_flac":0,"mv":"","album_audio_id":341673946,"all_privs":{"4":{"status":0,"privilege":5,"fail_process":0},"6":{"status":0,"privilege":5,"fail_process":0},"3":{"status":0,"privilege":5,"fail_process":0},"5":{"status":0,"privilege":5,"fail_process":0}},"vip":0,"type_flac":"","price_128":0,"hmvhash":"","hash":"F0C9D8310A9EB43001612890E181798D","size":"2446937","ismvfilehead":0,"filesize_super":0,"musictrac":0,"old_cpy":0,"fail_process":4,"320size":"6116903","320time":"152000","fail_process_128":0,"320hash":"0A6D9E509ED7209D757592A25C00083E","type":"audio","audio_id":122996979,"m4asize":0,"type_128":""},{"filesize_high":0,"hash_ape":"","pay_type_320":0,"hashflac":"41C67B2BDDABE000D85EE7946227D9CE","tracker_info":{},"topic_url":"","type_320":"","pkg_price_320":0,"sid":220489186,"topic_remark":"","filesize_ape":0,"bitrate":128,"isfilehead":100,"time":"240039","name":"宝石Gem、陈伟霆 - 野狼Disco","pkg_price_flac":0,"pay_type_flac":0,"320isfilehead":100,"hash_super":"","hash_high":"","fail_process_flac":0,"fail_process_320":0,"pay_type":3,"pkg_price_128":0,"album_id":"30181741","publish":1,"filesize_flac":26124807,"ext":"mp3","scid":60583588,"m4ahash":"","privilege_128":0,"_is_recommend":0,"privilege_flac":0,"price_320":0,"trac":"","mvtype":0,"privilege_320":0,"pay_type_128":0,"mvhash":"","trans_param":{"cpy_grade":5,"cpy_attr0":0,"cpy_level":1,"cid":77320812,"hash_multitrack":"91E34487E82251414084527575DD389D","pay_block_tpl":1,"display_rate":1,"classmap":{"attr0":100667400},"display":32,"musicpack_advance":0},"privilege":8,"price_flac":0,"mv":"","album_audio_id":220489186,"all_privs":{"4":{"privilege":10,"status":0,"trans_param":{"cpy_grade":5,"musicpack_advance":0,"cpy_level":1,"identity_block":1,"pay_block_tpl":1,"cpy_attr0":0,"display_rate":1,"classmap":{"attr0":100667400},"display":32,"cid":77320812},"pay_type":5,"fail_process":4},"6":{"privilege":10,"status":0,"trans_param":{"cpy_grade":5,"musicpack_advance":0,"cpy_level":1,"identity_block":1,"pay_block_tpl":1,"cpy_attr0":0,"display_rate":1,"classmap":{"attr0":100667400},"display":32,"cid":77320812},"pay_type":5,"fail_process":4},"3":{"status":0,"privilege":5,"fail_process":0},"5":{"privilege":10,"status":0,"trans_param":{"cpy_grade":5,"musicpack_advance":0,"cpy_level":1,"identity_block":1,"pay_block_tpl":1,"cpy_attr0":0,"display_rate":1,"classmap":{"attr0":100667400},"display":32,"cid":77320812},"pay_type":5,"fail_process":4}},"vip":0,"type_flac":"","price_128":0,"hmvhash":"","hash":"F3862988A4674098325C99A9CD664DB2","size":"3841306","ismvfilehead":0,"filesize_super":0,"musictrac":0,"old_cpy":1,"fail_process":4,"320size":"9602874","320time":"240039","fail_process_128":0,"320hash":"EC2CAA60B16BE49F2345622ABE4260E5","type":"audio","audio_id":60583588,"m4asize":0,"type_128":""},{"filesize_high":0,"hash_ape":"","pay_type_320":0,"hashflac":"47767A1233B142A2FAE7B9B89E501EC6","tracker_info":{},"topic_url":"","type_320":"","pkg_price_320":0,"sid":386822603,"topic_remark":"","filesize_ape":0,"bitrate":128,"isfilehead":100,"time":"270445","name":"李荣浩 - 脱胎换骨","pkg_price_flac":0,"pay_type_flac":0,"320isfilehead":100,"hash_super":"","hash_high":"","fail_process_flac":0,"fail_process_320":0,"pay_type":0,"pkg_price_128":0,"album_id":"55413681","publish":1,"filesize_flac":27791118,"ext":"mp3","scid":152123404,"m4ahash":"","privilege_128":0,"_is_recommend":0,"privilege_flac":0,"price_320":0,"trac":"","mvtype":0,"privilege_320":0,"pay_type_128":0,"mvhash":"","trans_param":{"cpy_grade":5,"musicpack_advance":0,"cpy_level":1,"cid":200219378,"pay_block_tpl":1,"classmap":{"attr0":100794376},"display_rate":2,"appid_block":"3124,2960,2966,3086,3004,3022,3056","display":8,"cpy_attr0":0},"privilege":0,"price_flac":0,"mv":"","album_audio_id":386822603,"all_privs":{"4":{"status":0,"privilege":5,"fail_process":0},"6":{"status":0,"privilege":5,"fail_process":0},"3":{"status":0,"privilege":5,"fail_process":0},"5":{"status":0,"privilege":5,"fail_process":0}},"vip":0,"type_flac":"","price_128":0,"hmvhash":"","hash":"B51B70C36FBE01A320626C27C7FD232B","size":"4327747","ismvfilehead":0,"filesize_super":0,"musictrac":0,"old_cpy":1,"fail_process":0,"320size":"10819045","320time":"270445","fail_process_128":0,"320hash":"13AA1730472BA140C54528E320584BDD","type":"audio","audio_id":152123404,"m4asize":0,"type_128":""},{"filesize_high":0,"hash_ape":"","pay_type_320":0,"hashflac":"A02A159E12960DCFF6521B0B209C51D6","tracker_info":{},"topic_url":"","type_320":"","pkg_price_320":0,"sid":246963986,"topic_remark":"","filesize_ape":0,"bitrate":128,"isfilehead":100,"time":"284000","name":"付豪 - 再也不是你","pkg_price_flac":0,"pay_type_flac":0,"320isfilehead":100,"hash_super":"","hash_high":"","fail_process_flac":0,"fail_process_320":0,"pay_type":3,"pkg_price_128":0,"album_id":"35763241","publish":1,"filesize_flac":29918380,"ext":"mp3","scid":66028200,"m4ahash":"","privilege_128":0,"_is_recommend":0,"privilege_flac":0,"price_320":0,"trac":"","mvtype":0,"privilege_320":0,"pay_type_128":0,"mvhash":"","trans_param":{"cpy_grade":5,"cpy_attr0":0,"cpy_level":1,"cid":86976147,"hash_multitrack":"3A9C293B6E5611DF5CF00C59569AE979","pay_block_tpl":1,"display_rate":0,"classmap":{"attr0":100663304},"display":0,"musicpack_advance":0},"privilege":8,"price_flac":0,"mv":"","album_audio_id":246963986,"all_privs":{"4":{"status":0,"privilege":5,"fail_process":0},"6":{"privilege":10,"status":0,"trans_param":{"cpy_grade":5,"musicpack_advance":0,"cpy_level":1,"identity_block":1,"pay_block_tpl":1,"cpy_attr0":0,"display_rate":0,"classmap":{"attr0":100663304},"display":0,"cid":86976147},"pay_type":1,"fail_process":4},"3":{"status":0,"privilege":5,"fail_process":0},"5":{"privilege":10,"status":0,"trans_param":{"cpy_grade":5,"musicpack_advance":0,"cpy_level":1,"identity_block":1,"pay_block_tpl":1,"cpy_attr0":0,"display_rate":0,"classmap":{"attr0":100663304},"display":0,"cid":86976147},"pay_type":1,"fail_process":4}},"vip":0,"type_flac":"","price_128":0,"hmvhash":"","hash":"FDD14B54537A00516B8AF4111F004F4D","size":"4545088","ismvfilehead":0,"filesize_super":0,"musictrac":0,"old_cpy":0,"fail_process":4,"320size":"11362420","320time":"284000","fail_process_128":0,"320hash":"D5BF378BF761D58D7C4373186E4195EA","type":"audio","audio_id":66028200,"m4asize":0,"type_128":""},{"filesize_high":0,"hash_ape":"","pay_type_320":0,"hashflac":"23214810A242765C9E721150593A2992","tracker_info":{},"topic_url":"","type_320":"","pkg_price_320":0,"sid":288019994,"topic_remark":"","filesize_ape":0,"bitrate":128,"isfilehead":100,"time":"220000","name":"薛之谦 - 野心","pkg_price_flac":0,"pay_type_flac":0,"320isfilehead":100,"hash_super":"","hash_high":"","fail_process_flac":0,"fail_process_320":0,"pay_type":3,"pkg_price_128":0,"album_id":"40890018","publish":1,"filesize_flac":26730604,"ext":"mp3","scid":88746641,"m4ahash":"","privilege_128":0,"_is_recommend":0,"privilege_flac":0,"price_320":0,"trac":"","mvtype":0,"privilege_320":0,"pay_type_128":0,"mvhash":"","trans_param":{"cpy_grade":5,"musicpack_advance":0,"cpy_level":1,"cid":124977962,"hash_multitrack":"EC6C9AD2FBBA1C86AD8B191E30C3AC15","pay_block_tpl":1,"classmap":{"attr0":100663304},"display_rate":0,"appid_block":"3124","display":0,"cpy_attr0":0},"privilege":8,"price_flac":0,"mv":"","album_audio_id":288019994,"all_privs":{"4":{"status":0,"privilege":5,"fail_process":0},"6":{"privilege":10,"status":0,"trans_param":{"cpy_grade":5,"cpy_attr0":0,"cpy_level":1,"identity_block":1,"musicpack_advance":0,"pay_block_tpl":1,"classmap":{"attr0":100663304},"display_rate":0,"appid_block":"3124","display":0,"cid":124977962},"pay_type":1,"fail_process":4},"3":{"status":0,"privilege":5,"fail_process":0},"5":{"privilege":10,"status":0,"trans_param":{"cpy_grade":5,"cpy_attr0":0,"cpy_level":1,"identity_block":1,"musicpack_advance":0,"pay_block_tpl":1,"classmap":{"attr0":100663304},"display_rate":0,"appid_block":"3124","display":0,"cid":124977962},"pay_type":1,"fail_process":4}},"vip":0,"type_flac":"","price_128":0,"hmvhash":"","hash":"A2544E395C12DE34F6D3F6C75E8DE955","size":"3521496","ismvfilehead":0,"filesize_super":0,"musictrac":0,"old_cpy":0,"fail_process":4,"320size":"8803455","320time":"220055","fail_process_128":0,"320hash":"1F2ABB109CD8585EB9635BBB213E5F8D","type":"audio","audio_id":88746641,"m4asize":0,"type_128":""},{"filesize_high":0,"hash_ape":"","pay_type_320":0,"hashflac":"E48F878B0E565A43BC59D0079EF5B43A","tracker_info":{},"topic_url":"","type_320":"","pkg_price_320":0,"sid":232286267,"topic_remark":"","filesize_ape":0,"bitrate":128,"isfilehead":100,"time":"232000","name":"王小帅 - 挥着翅膀的女孩","pkg_price_flac":0,"pay_type_flac":0,"320isfilehead":100,"hash_super":"","hash_high":"","fail_process_flac":0,"fail_process_320":0,"pay_type":3,"pkg_price_128":0,"album_id":"33056886","publish":1,"filesize_flac":27968852,"ext":"mp3","scid":62826611,"m4ahash":"","privilege_128":0,"_is_recommend":0,"privilege_flac":0,"price_320":0,"trac":"","mvtype":0,"privilege_320":0,"pay_type_128":0,"mvhash":"","trans_param":{"cpy_grade":5,"musicpack_advance":0,"cpy_level":1,"cid":80714672,"hash_multitrack":"F7FCF16D58290C2445890C11560F7687","pay_block_tpl":1,"classmap":{"attr0":100667400},"display_rate":1,"appid_block":"3124","display":32,"cpy_attr0":0},"privilege":8,"price_flac":0,"mv":"","album_audio_id":232286267,"all_privs":{"4":{"status":0,"privilege":5,"fail_process":0},"6":{"privilege":10,"status":0,"trans_param":{"cpy_grade":5,"cpy_attr0":0,"cpy_level":1,"identity_block":1,"musicpack_advance":0,"pay_block_tpl":1,"classmap":{"attr0":100667400},"display_rate":1,"appid_block":"3124","display":32,"cid":80714672},"pay_type":1,"fail_process":4},"3":{"status":0,"privilege":5,"fail_process":0},"5":{"privilege":10,"status":0,"trans_param":{"cpy_grade":5,"cpy_attr0":0,"cpy_level":1,"identity_block":1,"musicpack_advance":0,"pay_block_tpl":1,"classmap":{"attr0":100667400},"display_rate":1,"appid_block":"3124","display":32,"cid":80714672},"pay_type":1,"fail_process":4}},"vip":0,"type_flac":"","price_128":0,"hmvhash":"","hash":"CFB09B55E1F618A9B09937F694A6ACB4","size":"3717121","ismvfilehead":0,"filesize_super":0,"musictrac":0,"old_cpy":0,"fail_process":4,"320size":"9292109","320time":"232000","fail_process_128":0,"320hash":"409A1EDF69DA0997E3855D8796D8C120","type":"audio","audio_id":62826611,"m4asize":0,"type_128":""},{"filesize_high":0,"hash_ape":"","pay_type_320":0,"hashflac":"99A0D14ADFFA43C8D3630C5A2AF4A747","tracker_info":{},"topic_url":"","type_320":"","pkg_price_320":0,"sid":160149536,"topic_remark":"","filesize_ape":0,"bitrate":128,"isfilehead":100,"time":"245472","name":"Lil Ghost小鬼 - 别叫我达芬奇","pkg_price_flac":0,"pay_type_flac":0,"320isfilehead":100,"hash_super":"","hash_high":"","fail_process_flac":0,"fail_process_320":0,"pay_type":3,"pkg_price_128":0,"album_id":"22197783","publish":1,"filesize_flac":28832888,"ext":"mp3","scid":54477774,"m4ahash":"","privilege_128":0,"_is_recommend":0,"privilege_flac":0,"price_320":0,"trac":"","mvtype":0,"privilege_320":0,"pay_type_128":0,"mvhash":"","trans_param":{"cpy_grade":5,"musicpack_advance":0,"cpy_level":1,"cid":102314704,"hash_multitrack":"F27CD62E8789F06275F373B0E3099220","pay_block_tpl":1,"classmap":{"attr0":100667400},"display_rate":1,"appid_block":"3124","display":32,"cpy_attr0":0},"privilege":8,"price_flac":0,"mv":"","album_audio_id":160149536,"all_privs":{"4":{"status":0,"privilege":5,"fail_process":0},"6":{"privilege":10,"status":0,"trans_param":{"cpy_grade":5,"cpy_attr0":0,"cpy_level":1,"identity_block":1,"musicpack_advance":0,"pay_block_tpl":1,"classmap":{"attr0":100667400},"display_rate":1,"appid_block":"3124","display":32,"cid":102314704},"pay_type":1,"fail_process":4},"3":{"status":0,"privilege":5,"fail_process":0},"5":{"privilege":10,"status":0,"trans_param":{"cpy_grade":5,"cpy_attr0":0,"cpy_level":1,"identity_block":1,"musicpack_advance":0,"pay_block_tpl":1,"classmap":{"attr0":100667400},"display_rate":1,"appid_block":"3124","display":32,"cid":102314704},"pay_type":1,"fail_process":4}},"vip":0,"type_flac":"","price_128":0,"hmvhash":"","hash":"411540918A9A7A03C50C8823E7A784EA","size":"3928024","ismvfilehead":0,"filesize_super":0,"musictrac":0,"old_cpy":0,"fail_process":4,"320size":"9819995","320time":"245472","fail_process_128":0,"320hash":"A9EEF5ED9FB55BB308E728ECC14622AE","type":"audio","audio_id":54477774,"m4asize":0,"type_128":""},{"filesize_high":0,"hash_ape":"","pay_type_320":0,"hashflac":"4416C5D5FA1E6E3915E4E3E21F29C8ED","tracker_info":{},"topic_url":"","type_320":"","pkg_price_320":0,"sid":334539634,"topic_remark":"","filesize_ape":0,"bitrate":128,"isfilehead":100,"time":"237000","name":"任嘉伦 - 如一 (《周生如故》影视剧周生辰人物主题曲)","pkg_price_flac":0,"pay_type_flac":0,"320isfilehead":100,"hash_super":"","hash_high":"","fail_process_flac":0,"fail_process_320":0,"pay_type":3,"pkg_price_128":0,"album_id":"48463780","publish":1,"filesize_flac":28968304,"ext":"mp3","scid":117279645,"m4ahash":"","privilege_128":0,"_is_recommend":0,"privilege_flac":0,"price_320":0,"trac":"","mvtype":0,"privilege_320":0,"pay_type_128":0,"mvhash":"","trans_param":{"cpy_grade":5,"cpy_attr0":0,"cpy_level":1,"cid":165783891,"hash_multitrack":"12DCF4E97953FB1FA1A80183632D3357","pay_block_tpl":1,"display_rate":1,"classmap":{"attr0":100667400},"display":32,"musicpack_advance":0},"privilege":8,"price_flac":0,"mv":"","album_audio_id":334539634,"all_privs":{"4":{"status":0,"privilege":5,"fail_process":0},"6":{"privilege":10,"status":0,"trans_param":{"cpy_grade":5,"musicpack_advance":0,"cpy_level":1,"identity_block":1,"pay_block_tpl":1,"cpy_attr0":0,"display_rate":1,"classmap":{"attr0":100667400},"display":32,"cid":165783891},"pay_type":1,"fail_process":4},"3":{"status":0,"privilege":5,"fail_process":0},"5":{"privilege":10,"status":0,"trans_param":{"cpy_grade":5,"musicpack_advance":0,"cpy_level":1,"identity_block":1,"pay_block_tpl":1,"cpy_attr0":0,"display_rate":1,"classmap":{"attr0":100667400},"display":32,"cid":165783891},"pay_type":1,"fail_process":4}},"vip":0,"type_flac":"","price_128":0,"hmvhash":"","hash":"4335991A00AF55AE4DF1C50345AACC32","size":"3803618","ismvfilehead":0,"filesize_super":0,"musictrac":0,"old_cpy":0,"fail_process":4,"320size":"9508761","320time":"237000","fail_process_128":0,"320hash":"0DD6EB48851FDD45FB0389321DA76982","type":"audio","audio_id":117279645,"m4asize":0,"type_128":""},{"filesize_high":0,"hash_ape":"","pay_type_320":0,"hashflac":"269BF763094D0C6DFA41AA73B8063325","tracker_info":{},"topic_url":"","type_320":"","pkg_price_320":0,"sid":107172053,"topic_remark":"","filesize_ape":0,"bitrate":128,"isfilehead":100,"time":"209000","name":"小潘潘（潘柚彤）、小峰峰(陈峰) - 学猫叫","pkg_price_flac":0,"pay_type_flac":0,"320isfilehead":100,"hash_super":"","hash_high":"","fail_process_flac":0,"fail_process_320":0,"pay_type":3,"pkg_price_128":0,"album_id":"8496641","publish":1,"filesize_flac":26863236,"ext":"mp3","scid":37691754,"m4ahash":"","privilege_128":0,"_is_recommend":0,"privilege_flac":0,"price_320":0,"trac":"","mvtype":0,"privilege_320":0,"pay_type_128":0,"mvhash":"","trans_param":{"cpy_grade":5,"musicpack_advance":0,"cpy_level":1,"cid":32913230,"hash_multitrack":"D126F26B93DF57964A0F97952818CB77","pay_block_tpl":1,"classmap":{"attr0":100667400},"display_rate":1,"appid_block":"3124","display":32,"cpy_attr0":0},"privilege":8,"price_flac":0,"mv":"","album_audio_id":107172053,"all_privs":{"4":{"status":0,"privilege":5,"fail_process":0},"6":{"status":0,"privilege":5,"fail_process":0},"3":{"status":0,"privilege":5,"fail_process":0},"5":{"status":0,"privilege":5,"fail_process":0}},"vip":0,"type_flac":"","price_128":0,"hmvhash":"","hash":"F0AC7416D67BFEA235B5DCB62B0C5C1E","size":"3348909","ismvfilehead":0,"filesize_super":0,"musictrac":0,"old_cpy":1,"fail_process":4,"320size":"8371942","320time":"209000","fail_process_128":0,"320hash":"1C828A928FEEB14A4F6D308F89C42371","type":"audio","audio_id":37691754,"m4asize":0,"type_128":""},{"filesize_high":0,"hash_ape":"","pay_type_320":0,"hashflac":"1D3A05C47699F39D70D3A6C2B7A4BD8F","tracker_info":{},"topic_url":"","type_320":"","pkg_price_320":0,"sid":249852288,"topic_remark":"","filesize_ape":0,"bitrate":128,"isfilehead":100,"time":"298605","name":"半吨兄弟 - 女人的选择","pkg_price_flac":0,"pay_type_flac":0,"320isfilehead":100,"hash_super":"","hash_high":"","fail_process_flac":0,"fail_process_320":0,"pay_type":3,"pkg_price_128":0,"album_id":"36331668","publish":1,"filesize_flac":30398795,"ext":"mp3","scid":60550734,"m4ahash":"","privilege_128":0,"_is_recommend":0,"privilege_flac":0,"price_320":0,"trac":"","mvtype":0,"privilege_320":0,"pay_type_128":0,"mvhash":"","trans_param":{"cpy_grade":5,"cpy_attr0":0,"cpy_level":1,"cid":90650573,"hash_multitrack":"938B31466086E84444DBFFC13529EEA2","pay_block_tpl":1,"display_rate":1,"classmap":{"attr0":100667400},"display":32,"musicpack_advance":0},"privilege":8,"price_flac":0,"mv":"","album_audio_id":249852288,"all_privs":{"4":{"status":0,"privilege":5,"fail_process":0},"6":{"privilege":10,"status":0,"trans_param":{"cpy_grade":5,"musicpack_advance":0,"cpy_level":1,"identity_block":1,"pay_block_tpl":1,"cpy_attr0":0,"display_rate":1,"classmap":{"attr0":100667400},"display":32,"cid":90650573},"pay_type":1,"fail_process":4},"3":{"status":0,"privilege":5,"fail_process":0},"5":{"privilege":10,"status":0,"trans_param":{"cpy_grade":5,"musicpack_advance":0,"cpy_level":1,"identity_block":1,"pay_block_tpl":1,"cpy_attr0":0,"display_rate":1,"classmap":{"attr0":100667400},"display":32,"cid":90650573},"pay_type":1,"fail_process":4}},"vip":0,"type_flac":"","price_128":0,"hmvhash":"","hash":"190949012000191D2AE440A497C098E4","size":"4778313","ismvfilehead":0,"filesize_super":0,"musictrac":0,"old_cpy":0,"fail_process":4,"320size":"11945423","320time":"299000","fail_process_128":0,"320hash":"F9D60B97D675321CDB03813DBA190A1E","type":"audio","audio_id":60550734,"m4asize":0,"type_128":""},{"filesize_high":0,"hash_ape":"","pay_type_320":0,"hashflac":"9C0D2437E78C2CCA81BA5A54EC11896B","tracker_info":{},"topic_url":"","type_320":"","pkg_price_320":0,"sid":400138515,"topic_remark":"","filesize_ape":0,"bitrate":128,"isfilehead":100,"time":"182047","name":"陈子晴 - 陪你看日落","pkg_price_flac":0,"pay_type_flac":0,"320isfilehead":100,"hash_super":"","hash_high":"","fail_process_flac":0,"fail_process_320":0,"pay_type":3,"pkg_price_128":0,"album_id":"56329701","publish":1,"filesize_flac":19598210,"ext":"mp3","scid":152485233,"m4ahash":"","privilege_128":0,"_is_recommend":0,"privilege_flac":0,"price_320":0,"trac":"","mvtype":0,"privilege_320":0,"pay_type_128":0,"mvhash":"","trans_param":{"cpy_grade":5,"cpy_attr0":0,"cpy_level":1,"cid":205631833,"pay_block_tpl":1,"display_rate":0,"classmap":{"attr0":100663304},"display":0,"musicpack_advance":0},"privilege":8,"price_flac":0,"mv":"","album_audio_id":400138515,"all_privs":{"4":{"status":0,"privilege":5,"fail_process":0},"6":{"privilege":10,"status":0,"trans_param":{"cpy_grade":5,"musicpack_advance":0,"cpy_level":1,"identity_block":1,"pay_block_tpl":1,"cpy_attr0":0,"display_rate":0,"classmap":{"attr0":100663304},"display":0,"cid":205631833},"pay_type":1,"fail_process":4},"3":{"status":0,"privilege":5,"fail_process":0},"5":{"privilege":10,"status":0,"trans_param":{"cpy_grade":5,"musicpack_advance":0,"cpy_level":1,"identity_block":1,"pay_block_tpl":1,"cpy_attr0":0,"display_rate":0,"classmap":{"attr0":100663304},"display":0,"cid":205631833},"pay_type":1,"fail_process":4}},"vip":0,"type_flac":"","price_128":0,"hmvhash":"","hash":"A6967A5267B5705207FD50B0597D25C7","size":"2913377","ismvfilehead":0,"filesize_super":0,"musictrac":0,"old_cpy":0,"fail_process":4,"320size":"7283140","320time":"182000","fail_process_128":0,"320hash":"037FF48E30418050CE7E1CB96E7A4515","type":"audio","audio_id":152485233,"m4asize":0,"type_128":""}]}]}
