{"error_code":0,"data":{"offset":14,"songlist":[{"audio_info":{"duration_128":186000,"hash_128":"5C226533B0DD8C587EE2B47731634039","filesize_128":2982800},"audio_name":"In Your Arms","author_name":"Kina Grannis","privilege_play":{"privilege_128":0},"album_info":{"album_name":"Stairwells (楼梯井)","album_id":11249407,"sizable_cover":"http:\/\/imge.kugou.com\/stdmusic\/{size}\/20160908\/20160908134530832281.jpg"},"album_audio_id":118241430},{"audio_info":{"duration_128":176000,"hash_128":"4EAB6CC48BBDAD3A521E24F772F9D7A5","filesize_128":2820236},"audio_name":"After Midnight","author_name":"KLYMVX、Emily Zeck","privilege_play":{"privilege_128":8},"album_info":{"album_name":"After Midnight","album_id":1943701,"sizable_cover":"http:\/\/imge.kugou.com\/stdmusic\/{size}\/20200812\/20200812142205454526.jpg"},"album_audio_id":52935334},{"audio_info":{"duration_128":206000,"hash_128":"754AA22BFEFFCB99A48D673E7F3D6F83","filesize_128":3297974},"audio_name":"I Really Like You","author_name":"Carly Rae Jepsen","privilege_play":{"privilege_128":8},"album_info":{"album_name":"I Really Like You","album_id":2429418,"sizable_cover":"http:\/\/imge.kugou.com\/stdmusic\/{size}\/20170508\/20170508010413144821.jpg"},"album_audio_id":62473149},{"audio_info":{"duration_128":220000,"hash_128":"A43A97D206A1A952BB9BAC4EDE030C74","filesize_128":3530341},"audio_name":"Can't Stop Love","author_name":"Darin","privilege_play":{"privilege_128":8},"album_info":{"album_name":"Lovekiller","album_id":966340,"sizable_cover":"http:\/\/imge.kugou.com\/stdmusic\/{size}\/20150718\/20150718121339150702.jpg"},"album_audio_id":32096081},{"audio_info":{"duration_128":219533,"hash_128":"BD0C309B491046984CE4C271F25345C3","filesize_128":3513231},"audio_name":"Everyday, Everyday","author_name":"Manila Killa、Nevve","privilege_play":{"privilege_128":8},"album_info":{"album_name":"Everyday, Everyday","album_id":14816090,"sizable_cover":"http:\/\/imge.kugou.com\/stdmusic\/{size}\/20190125\/20190125162837628302.jpg"},"album_audio_id":106073737},{"audio_info":{"duration_128":207000,"hash_128":"0558380BD190CD4386807306563373E7","filesize_128":3320121},"audio_name":"First Love","author_name":"Lost Kings、Sabrina Carpenter","privilege_play":{"privilege_128":8},"album_info":{"album_name":"First Love","album_id":4112279,"sizable_cover":"http:\/\/imge.kugou.com\/stdmusic\/{size}\/20171013\/20171013050023776733.jpg"},"album_audio_id":89402369},{"audio_info":{"duration_128":205000,"hash_128":"8D31EA3231A80638EFB4A75910CA44FC","filesize_128":3292536},"audio_name":"Waiting","author_name":"Vicetone、Daisy Guttridge、Eric Leva","privilege_play":{"privilege_128":8},"album_info":{"album_name":"Waiting","album_id":20401650,"sizable_cover":"http:\/\/imge.kugou.com\/stdmusic\/{size}\/20190511\/20190511070604456240.jpg"},"album_audio_id":152253296},{"audio_info":{"duration_128":201000,"hash_128":"E9D71F9D88613E4609D90B27F3F52149","filesize_128":3226153},"audio_name":"Strawberries & Cigarettes","author_name":"Troye Sivan","privilege_play":{"privilege_128":8},"album_info":{"album_name":"Love, Simon (Original Motion Picture Soundtrack)","album_id":8305723,"sizable_cover":"http:\/\/imge.kugou.com\/stdmusic\/{size}\/20180116\/20180116112552264941.jpg"},"album_audio_id":106700215},{"audio_info":{"duration_128":213000,"hash_128":"2388ACD95F31767B27B28666D618A41A","filesize_128":3420346},"audio_name":"U","author_name":"John Park","privilege_play":{"privilege_128":8},"album_info":{"album_name":"U","album_id":974593,"sizable_cover":"http:\/\/imge.kugou.com\/stdmusic\/{size}\/20211109\/20211109144306328867.jpg"},"album_audio_id":32169341},{"audio_info":{"duration_128":218000,"hash_128":"5325E22E891609BCF5219778719FF8F2","filesize_128":3494802},"audio_name":"Unbreakable","author_name":"Janet Jackson","privilege_play":{"privilege_128":8},"album_info":{"album_name":"Unbreakable (坚不可摧)","album_id":4050805,"sizable_cover":"http:\/\/imge.kugou.com\/stdmusic\/{size}\/20160909\/20160909010354226814.jpg"},"album_audio_id":88549801},{"audio_info":{"duration_128":263000,"hash_128":"BBC7B86E3BBCBF2CE1B2A30C82EFD546","filesize_128":4215764},"audio_name":"Perfect","author_name":"Ed Sheeran","privilege_play":{"privilege_128":10},"album_info":{"album_name":"÷ (Deluxe)","album_id":1971008,"sizable_cover":"http:\/\/imge.kugou.com\/stdmusic\/{size}\/20200909\/20200909112422386535.jpg"},"album_audio_id":54097809},{"audio_info":{"duration_128":200000,"hash_128":"77796EB58861CE6B83201F17DA9CC6E1","filesize_128":3216062},"audio_name":"Ready or Not","author_name":"Bridgit Mendler","privilege_play":{"privilege_128":8},"album_info":{"album_name":"Ready or Not (Remixes) - EP","album_id":585553,"sizable_cover":"http:\/\/imge.kugou.com\/stdmusic\/{size}\/20150720\/20150720110007355249.jpg"},"album_audio_id":62019255},{"audio_info":{"duration_128":200306,"hash_128":"87D247A2ADF5A580C9E75E8D7D23CE92","filesize_128":3205498},"audio_name":"Be My Forever","author_name":"Christina Perri、Ed Sheeran","privilege_play":{"privilege_128":0},"album_info":{"album_name":"Head Or Heart","album_id":958604,"sizable_cover":"http:\/\/imge.kugou.com\/stdmusic\/{size}\/20211103\/20211103092604316969.jpg"},"album_audio_id":32026943},{"audio_info":{"duration_128":218357,"hash_128":"ACFACDEABFC6DF6B4009C275B32893D6","filesize_128":3494430},"audio_name":"Beautiful Now","author_name":"Zedd、Jon Bellion","privilege_play":{"privilege_128":8},"album_info":{"album_name":"True Colors (Perfect Edition)","album_id":547467,"sizable_cover":"http:\/\/imge.kugou.com\/stdmusic\/{size}\/20200909\/20200909121145294627.jpg"},"album_audio_id":28013169},{"audio_info":{"duration_128":181054,"hash_128":"C08A51779A9DCDE9B25CBC0F3ED056DF","filesize_128":2897541},"audio_name":"Sucker","author_name":"Jonas Brothers","privilege_play":{"privilege_128":8},"album_info":{"album_name":"Happiness Begins","album_id":22259719,"sizable_cover":"http:\/\/imge.kugou.com\/stdmusic\/{size}\/20190607\/20190607122805459117.jpg"},"album_audio_id":160403136},{"audio_info":{"duration_128":206000,"hash_128":"49296F8D5A30A4A9117980F516FD3AC6","filesize_128":3299635},"audio_name":"Shock Me Into Love","author_name":"Lenka","privilege_play":{"privilege_128":10},"album_info":{"album_name":"Two (Expanded Edition)","album_id":20096755,"sizable_cover":"http:\/\/imge.kugou.com\/stdmusic\/{size}\/20190507\/20190507013602935367.jpg"},"album_audio_id":150612712},{"audio_info":{"duration_128":212000,"hash_128":"F62AD5BB64094461F5121161B421E0A4","filesize_128":3394920},"audio_name":"Retro Romance","author_name":"Alexx Mack","privilege_play":{"privilege_128":8},"album_info":{"album_name":"Like We're Famous","album_id":1063071,"sizable_cover":"http:\/\/imge.kugou.com\/stdmusic\/{size}\/20151222\/20151222022306989138.jpg"},"album_audio_id":33049836},{"audio_info":{"duration_128":196000,"hash_128":"CF73260A221DEF3838279607E641329D","filesize_128":3150924},"audio_name":"Shut Up and Dance (NOW What's Next!)","author_name":"WALK THE MOON","privilege_play":{"privilege_128":8},"album_info":{"album_name":"Now That's What I Call Music, Vol. 53","album_id":546803,"sizable_cover":"http:\/\/imge.kugou.com\/stdmusic\/{size}\/20200909\/20200909121005273584.jpg"},"album_audio_id":27981730},{"audio_info":{"duration_128":281000,"hash_128":"B46CB461411AADBC4609069E015CE2AD","filesize_128":4506284},"audio_name":"Thinking Out Loud","author_name":"Ed Sheeran","privilege_play":{"privilege_128":10},"album_info":{"album_name":"X (Deluxe Edition)","album_id":3715027,"sizable_cover":"http:\/\/imge.kugou.com\/stdmusic\/{size}\/20210113\/20210113155531760599.jpg"},"album_audio_id":83067239},{"audio_info":{"duration_128":228000,"hash_128":"9D4864FFE8262379B206C66B4AD1D27F","filesize_128":3651593},"audio_name":"The Best Days Of My Life","author_name":"Jason Gray","privilege_play":{"privilege_128":10},"album_info":{"album_name":"Love Will Have the Final Word","album_id":977707,"sizable_cover":"http:\/\/imge.kugou.com\/stdmusic\/{size}\/20150720\/20150720193438539626.jpg"},"album_audio_id":32197465}]},"status":1}
