{"error_code":0,"data":{"offset":20,"songlist":[{"audio_info":{"duration_128":172000,"hash_128":"62FB9C2AFA9FF0C284CC5DA5555AEA3F","filesize_128":2765679},"audio_name":"#C0C0C0","author_name":"XIKINIE","privilege_play":{"privilege_128":8},"album_info":{"album_name":"#C0C0C0","album_id":42235150,"sizable_cover":"http:\/\/imge.kugou.com\/stdmusic\/{size}\/20210304\/20210304143913229026.jpg"},"album_audio_id":298431447},{"audio_info":{"duration_128":107000,"hash_128":"F025FE4A6FAEB877102764104F3F6982","filesize_128":1720417},"audio_name":"巴黎恋人 (轻音乐)","author_name":"轻音乐馆","privilege_play":{"privilege_128":8},"album_info":{"album_name":"美容院音乐轻松\/店铺音乐轻松音乐\/美容院轻音乐","album_id":45281518,"sizable_cover":"http:\/\/imge.kugou.com\/stdmusic\/{size}\/20210603\/20210603103615543496.jpg"},"album_audio_id":317385161},{"audio_info":{"duration_128":136000,"hash_128":"DF1E144BEABA7FC8082BD5B6C41EE3D8","filesize_128":2180327},"audio_name":"浪淘沙 ·九曲黄河万里沙 (钢琴独奏版)","author_name":"许荣","privilege_play":{"privilege_128":8},"album_info":{"album_name":"诗词钢琴曲 (独奏版) 五","album_id":45286412,"sizable_cover":"http:\/\/imge.kugou.com\/stdmusic\/{size}\/20210603\/20210603155005505168.jpg"},"album_audio_id":317422914},{"audio_info":{"duration_128":108000,"hash_128":"080FB7C4144A948A188F456729013B1D","filesize_128":1744187},"audio_name":"胎教音乐宝宝安眠曲 (八音盒版)","author_name":"顾可勋","privilege_play":{"privilege_128":8},"album_info":{"album_name":"减压催眠曲、舒缓的音乐、快速入睡音乐","album_id":42217089,"sizable_cover":"http:\/\/imge.kugou.com\/stdmusic\/{size}\/20210303\/20210303232906197182.jpg"},"album_audio_id":298617431},{"audio_info":{"duration_128":249495,"hash_128":"6E6B95CEB6988665277C73B7B7C57827","filesize_128":3993604},"audio_name":"爱的真谛","author_name":"助眠纯音乐","privilege_play":{"privilege_128":0},"album_info":{"album_name":"班得瑞全集：14CD 201首","album_id":54694730,"sizable_cover":"http:\/\/imge.kugou.com\/stdmusic\/{size}\/20220216\/20220216170659348503.png"},"album_audio_id":381343487},{"audio_info":{"duration_128":301635,"hash_128":"3F1B0CB82AF4E9E637BD4BBC472316DA","filesize_128":4826872},"audio_name":"山顶日出(流水声、手风琴、短笛、提琴)","author_name":"助眠减压催眠曲","privilege_play":{"privilege_128":0},"album_info":{"album_name":"大自然与轻音乐的交织：宝宝哄睡，婴儿催眠曲，放松解压","album_id":39776978,"sizable_cover":"http:\/\/imge.kugou.com\/stdmusic\/{size}\/20200715\/20200715211421160045.jpg"},"album_audio_id":278568646},{"audio_info":{"duration_128":141000,"hash_128":"30B729B7CBFDE50DB5A64DDFBD1D3888","filesize_128":2268558},"audio_name":"慕容杰伦与美如","author_name":"小冬","privilege_play":{"privilege_128":8},"album_info":{"album_name":"我的巴比伦恋人 网络剧原声大碟","album_id":49555605,"sizable_cover":"http:\/\/imge.kugou.com\/stdmusic\/{size}\/20211015\/20211015163103785103.jpg"},"album_audio_id":342930242},{"audio_info":{"duration_128":77000,"hash_128":"EFFC89F34AA26CDB60D882FDF822A993","filesize_128":1241126},"audio_name":"光与雾","author_name":"胡小鸥","privilege_play":{"privilege_128":8},"album_info":{"album_name":"赘婿 电视剧原声带","album_id":42029886,"sizable_cover":"http:\/\/imge.kugou.com\/stdmusic\/{size}\/20210223\/20210223144201786878.jpg"},"album_audio_id":297210018},{"audio_info":{"duration_128":108000,"hash_128":"D0D3038076C918980C8FC326B6BAFBBE","filesize_128":1740008},"audio_name":"找尾巴","author_name":"离羽墨","privilege_play":{"privilege_128":8},"album_info":{"album_name":"中外经典儿歌钢琴合集","album_id":43243973,"sizable_cover":"http:\/\/imge.kugou.com\/stdmusic\/{size}\/20210401\/20210401153018894170.jpg"},"album_audio_id":305794639},{"audio_info":{"duration_128":128312,"hash_128":"8D918CBBA89BA41E2C6C560F59B5A366","filesize_128":2053578},"audio_name":"原创纯音乐 |心安处静观潮汐","author_name":"音乐人梦果","privilege_play":{"privilege_128":0},"album_info":{"album_name":"大自然疗愈纯音乐 | 深度放松 助眠减压 清除负能量","album_id":44696149,"sizable_cover":"http:\/\/imge.kugou.com\/stdmusic\/{size}\/20220303\/20220303151606471272.jpg"},"album_audio_id":313926641},{"audio_info":{"duration_128":265000,"hash_128":"BA2BB87586EBBA3CD89D6F32B5A6CE31","filesize_128":4250926},"audio_name":"I Will Still Love You","author_name":"Isaac Shepard","privilege_play":{"privilege_128":8},"album_info":{"album_name":"Knights and Damsels","album_id":569776,"sizable_cover":"http:\/\/imge.kugou.com\/stdmusic\/{size}\/20150716\/20150716011150281401.jpg"},"album_audio_id":28298080},{"audio_info":{"duration_128":172512,"hash_128":"51F5A62957CE87461C8F451555CB50C7","filesize_128":2760765},"audio_name":"你的微笑","author_name":"酷有声","privilege_play":{"privilege_128":0},"album_info":{"album_name":"睡觉轻音乐，再听10分钟就睡觉","album_id":43569363,"sizable_cover":"http:\/\/imge.kugou.com\/stdmusic\/{size}\/20211028\/20211028174511558869.png"},"album_audio_id":308564978},{"audio_info":{"duration_128":145084,"hash_128":"54F573BA936C28F58038C2DAEF9273F9","filesize_128":2321807},"audio_name":"想去远方看山川 想去海边看海鸥","author_name":"轻音阁","privilege_play":{"privilege_128":8},"album_info":{"album_name":"都说爱难穿越四季","album_id":40620173,"sizable_cover":"http:\/\/imge.kugou.com\/stdmusic\/{size}\/20201216\/20201216161701260350.jpg"},"album_audio_id":285811551},{"audio_info":{"duration_128":296000,"hash_128":"39997052418BA7E209AE6356E96AFB59","filesize_128":4744024},"audio_name":"白露","author_name":"羽肿","privilege_play":{"privilege_128":8},"album_info":{"album_name":"白露","album_id":8455008,"sizable_cover":"http:\/\/imge.kugou.com\/stdmusic\/{size}\/20170525\/20170525122007637214.jpg"},"album_audio_id":58802959},{"audio_info":{"duration_128":181000,"hash_128":"B5045EA74F42A6178A6D802AB8FAE62C","filesize_128":2902098},"audio_name":"宝贝摇篮曲","author_name":"未知歌手","privilege_play":{"privilege_128":8},"album_info":{"album_name":"睡前安眠曲 - 最好听的催眠曲和钢琴曲为了让你迅速地入睡和好好休息","album_id":11022585,"sizable_cover":"http:\/\/imge.kugou.com\/stdmusic\/{size}\/20181001\/20181001094853817727.jpg"},"album_audio_id":117387352},{"audio_info":{"duration_128":102000,"hash_128":"F1AE4477400652EEAF8A7084AF015B2C","filesize_128":1638916},"audio_name":"久违放晴的天空 (钢琴曲)","author_name":"轻音乐馆","privilege_play":{"privilege_128":8},"album_info":{"album_name":"商场背景音乐\/商场轻音乐\/超市轻音乐\/店铺音乐","album_id":45429366,"sizable_cover":"http:\/\/imge.kugou.com\/stdmusic\/{size}\/20210609\/20210609132603406570.jpg"},"album_audio_id":318465512},{"audio_info":{"duration_128":205000,"hash_128":"448BC003A6FD7C835C12A4F9E9724762","filesize_128":3288410},"audio_name":"Garden of Grandpa 爷爷的花园 (爷爷的花园)","author_name":"郭芳菲","privilege_play":{"privilege_128":0},"album_info":{"album_name":"芳菲Fiona 旅行钢琴曲","album_id":39170929,"sizable_cover":"http:\/\/imge.kugou.com\/stdmusic\/{size}\/20201009\/20201009165631932692.jpg"},"album_audio_id":298310952},{"audio_info":{"duration_128":95000,"hash_128":"2EF0A4D19A80C3646C2F748806FB6D30","filesize_128":1521041},"audio_name":"背叛情歌","author_name":"蔡小雅","privilege_play":{"privilege_128":8},"album_info":{"album_name":"背叛情歌(抖音原版)","album_id":48592181,"sizable_cover":"http:\/\/imge.kugou.com\/stdmusic\/{size}\/20210906\/20210906184923993524.jpg"},"album_audio_id":335816384},{"audio_info":{"duration_128":3600039,"hash_128":"314C683E6821BB339E32567794E43AD3","filesize_128":57601262},"audio_name":"10 PM","author_name":"Yang Bao","privilege_play":{"privilege_128":8},"album_info":{"album_name":"GODSPEED","album_id":51438819,"sizable_cover":"http:\/\/imge.kugou.com\/stdmusic\/{size}\/20211217\/20211217161109141310.jpg"},"album_audio_id":359448193},{"audio_info":{"duration_128":96000,"hash_128":"161E4F90EA988A595B63829AA0F4F33E","filesize_128":1537297},"audio_name":"天空灰色了像哭了 (经典葫芦丝)","author_name":"轻松音乐","privilege_play":{"privilege_128":8},"album_info":{"album_name":"西餐厅音乐\/西餐厅浪漫音乐\/西餐厅轻音乐\/饭店音乐\/饭店轻音乐","album_id":40773512,"sizable_cover":"http:\/\/imge.kugou.com\/stdmusic\/{size}\/20210415\/20210415171310955493.jpg"},"album_audio_id":287051442}]},"status":1}
