{"status":1,"error_code":0,"data":[{"offset":40,"size":20,"fmid":1304,"fmtype":2,"songs":[{"filesize_high":0,"hash_ape":"","pay_type_320":0,"hashflac":"","tracker_info":{},"topic_url":"","type_320":"","pkg_price_320":0,"sid":126772203,"topic_remark":"","filesize_ape":0,"bitrate":128,"isfilehead":100,"time":"143000","name":"submarine boy、Ocoenia - Sleepyhead","pkg_price_flac":0,"pay_type_flac":0,"320isfilehead":100,"hash_super":"","hash_high":"","fail_process_flac":0,"fail_process_320":0,"pay_type":3,"pkg_price_128":0,"album_id":"19106683","publish":1,"filesize_flac":0,"ext":"mp3","scid":47612264,"m4ahash":"","privilege_128":0,"_is_recommend":0,"privilege_flac":0,"price_320":0,"trac":"","mvtype":0,"privilege_320":0,"pay_type_128":0,"mvhash":"","trans_param":{"cpy_grade":5,"cpy_attr0":0,"cpy_level":1,"cid":167001720,"hash_multitrack":"1235AA556087A33562A1B2695C220E90","pay_block_tpl":1,"display_rate":0,"classmap":{"attr0":100663304},"display":0,"musicpack_advance":0},"privilege":8,"price_flac":0,"mv":"","album_audio_id":126772203,"all_privs":{"4":{"status":0,"privilege":5,"fail_process":0},"6":{"privilege":10,"status":0,"trans_param":{"cpy_grade":5,"musicpack_advance":0,"cpy_level":1,"identity_block":1,"pay_block_tpl":1,"cpy_attr0":0,"display_rate":0,"classmap":{"attr0":100663304},"display":0,"cid":167001720},"pay_type":1,"fail_process":4},"3":{"status":0,"privilege":5,"fail_process":0},"5":{"privilege":10,"status":0,"trans_param":{"cpy_grade":5,"musicpack_advance":0,"cpy_level":1,"identity_block":1,"pay_block_tpl":1,"cpy_attr0":0,"display_rate":0,"classmap":{"attr0":100663304},"display":0,"cid":167001720},"pay_type":1,"fail_process":4}},"vip":0,"type_flac":"","price_128":0,"hmvhash":"","hash":"FC5E29F8FA928DE8E8E50D061D85FB19","size":"2290658","ismvfilehead":0,"filesize_super":0,"musictrac":0,"old_cpy":0,"fail_process":4,"320size":"5726283","320time":"143000","fail_process_128":0,"320hash":"05262744D2472FB407CF0CDC57E50362","type":"audio","audio_id":47612264,"m4asize":0,"type_128":""},{"filesize_high":0,"hash_ape":"","pay_type_320":0,"hashflac":"8B52626DC3938C6B3912F10C5A27CA68","tracker_info":{},"topic_url":"","type_320":"","pkg_price_320":0,"sid":308898206,"topic_remark":"","filesize_ape":0,"bitrate":128,"isfilehead":100,"time":"237000","name":"宴宁 - 纯白咒语","pkg_price_flac":0,"pay_type_flac":0,"320isfilehead":100,"hash_super":"","hash_high":"","fail_process_flac":0,"fail_process_320":0,"pay_type":3,"pkg_price_128":0,"album_id":"43622158","publish":1,"filesize_flac":26915886,"ext":"mp3","scid":104882993,"m4ahash":"","privilege_128":0,"_is_recommend":0,"privilege_flac":0,"price_320":0,"trac":"","mvtype":0,"privilege_320":0,"pay_type_128":0,"mvhash":"","trans_param":{"cpy_grade":5,"cpy_attr0":0,"cpy_level":1,"cid":145093548,"hash_multitrack":"0B8735B95158C1495B86B07436A88A89","pay_block_tpl":1,"display_rate":0,"classmap":{"attr0":100663304},"display":0,"musicpack_advance":0},"privilege":8,"price_flac":0,"mv":"","album_audio_id":308898206,"all_privs":{"4":{"status":0,"privilege":5,"fail_process":0},"6":{"privilege":10,"status":0,"trans_param":{"cpy_grade":5,"musicpack_advance":0,"cpy_level":1,"identity_block":1,"pay_block_tpl":1,"cpy_attr0":0,"display_rate":0,"classmap":{"attr0":100663304},"display":0,"cid":145093548},"pay_type":1,"fail_process":4},"3":{"status":0,"privilege":5,"fail_process":0},"5":{"privilege":10,"status":0,"trans_param":{"cpy_grade":5,"musicpack_advance":0,"cpy_level":1,"identity_block":1,"pay_block_tpl":1,"cpy_attr0":0,"display_rate":0,"classmap":{"attr0":100663304},"display":0,"cid":145093548},"pay_type":1,"fail_process":4}},"vip":0,"type_flac":"","price_128":0,"hmvhash":"","hash":"BAF51606F800030B9E73EAA37EA0785B","size":"3799445","ismvfilehead":0,"filesize_super":0,"musictrac":0,"old_cpy":1,"fail_process":4,"320size":"9498318","320time":"237000","fail_process_128":0,"320hash":"8CAF2E0E0CC9572A384202045A100B25","type":"audio","audio_id":104882993,"m4asize":0,"type_128":""},{"filesize_high":0,"hash_ape":"","pay_type_320":0,"hashflac":"452002D91426C29FDBB11B4DBA42A9BE","tracker_info":{},"topic_url":"","type_320":"","pkg_price_320":0,"sid":367635459,"topic_remark":"","filesize_ape":0,"bitrate":128,"isfilehead":100,"time":"349440","name":"鱼丁糸 - 频率 (鱼版)","pkg_price_flac":0,"pay_type_flac":0,"320isfilehead":100,"hash_super":"","hash_high":"","fail_process_flac":0,"fail_process_320":0,"pay_type":3,"pkg_price_128":0,"album_id":"52438511","publish":1,"filesize_flac":45977641,"ext":"mp3","scid":141783749,"m4ahash":"","privilege_128":0,"_is_recommend":0,"privilege_flac":0,"price_320":0,"trac":"","mvtype":0,"privilege_320":0,"pay_type_128":0,"mvhash":"","trans_param":{"cpy_grade":5,"cpy_attr0":0,"cpy_level":1,"cid":191849707,"hash_multitrack":"335148F4FBEDD8D1D7D0028CEB6BEA6E","pay_block_tpl":1,"display_rate":0,"classmap":{"attr0":100663304},"display":0,"musicpack_advance":0},"privilege":8,"price_flac":0,"mv":"","album_audio_id":367635459,"all_privs":{"4":{"status":0,"privilege":5,"fail_process":0},"6":{"privilege":10,"status":0,"trans_param":{"cpy_grade":5,"musicpack_advance":0,"cpy_level":1,"identity_block":1,"pay_block_tpl":1,"cpy_attr0":0,"display_rate":0,"classmap":{"attr0":100663304},"display":0,"cid":191849707},"pay_type":1,"fail_process":4},"3":{"status":0,"privilege":5,"fail_process":0},"5":{"privilege":10,"status":0,"trans_param":{"cpy_grade":5,"musicpack_advance":0,"cpy_level":1,"identity_block":1,"pay_block_tpl":1,"cpy_attr0":0,"display_rate":0,"classmap":{"attr0":100663304},"display":0,"cid":191849707},"pay_type":1,"fail_process":4}},"vip":0,"type_flac":"","price_128":0,"hmvhash":"","hash":"80ED09A294EAA15267E31EE6E017650D","size":"5591676","ismvfilehead":0,"filesize_super":0,"musictrac":0,"old_cpy":0,"fail_process":4,"320size":"13978863","320time":"349440","fail_process_128":0,"320hash":"FF81AD1B58ADE1F6A48338BFFAAD5467","type":"audio","audio_id":141783749,"m4asize":0,"type_128":""},{"filesize_high":0,"hash_ape":"","pay_type_320":0,"hashflac":"FD14255DE519F9E60614E289B6439482","tracker_info":{},"topic_url":"","type_320":"","pkg_price_320":0,"sid":128114602,"topic_remark":"","filesize_ape":0,"bitrate":128,"isfilehead":100,"time":"230006","name":"SAFIA - Freakin' Out","pkg_price_flac":0,"pay_type_flac":0,"320isfilehead":100,"hash_super":"","hash_high":"","fail_process_flac":0,"fail_process_320":0,"pay_type":3,"pkg_price_128":0,"album_id":"19078823","publish":1,"filesize_flac":28505736,"ext":"mp3","scid":43689760,"m4ahash":"","privilege_128":0,"_is_recommend":0,"privilege_flac":0,"price_320":0,"trac":"","mvtype":0,"privilege_320":0,"pay_type_128":0,"mvhash":"","trans_param":{"cpy_grade":5,"cpy_attr0":0,"cpy_level":1,"cid":79241656,"hash_multitrack":"88371944A32347E969B2301583A8494F","pay_block_tpl":1,"display_rate":0,"classmap":{"attr0":100663304},"display":0,"musicpack_advance":0},"privilege":8,"price_flac":0,"mv":"","album_audio_id":128114602,"all_privs":{"4":{"status":0,"privilege":5,"fail_process":0},"6":{"status":0,"privilege":5,"fail_process":0},"3":{"status":0,"privilege":5,"fail_process":0},"5":{"status":0,"privilege":5,"fail_process":0}},"vip":0,"type_flac":"","price_128":0,"hmvhash":"","hash":"02E5CAF8A508438701CBBB131ACAE382","size":"3681428","ismvfilehead":0,"filesize_super":0,"musictrac":0,"old_cpy":1,"fail_process":4,"320size":"9203505","320time":"230006","fail_process_128":0,"320hash":"E388F6074B5A951CA77B02F63747605E","type":"audio","audio_id":43689760,"m4asize":0,"type_128":""},{"filesize_high":0,"hash_ape":"","pay_type_320":0,"hashflac":"95BDA117B839FFD01365FFC07A13CCE5","tracker_info":{},"topic_url":"","type_320":"","pkg_price_320":0,"sid":287273748,"topic_remark":"","filesize_ape":0,"bitrate":128,"isfilehead":100,"time":"283611","name":"F U N乐队 - 成王败寇","pkg_price_flac":0,"pay_type_flac":0,"320isfilehead":100,"hash_super":"","hash_high":"","fail_process_flac":0,"fail_process_320":0,"pay_type":3,"pkg_price_128":0,"album_id":"40666174","publish":1,"filesize_flac":36972446,"ext":"mp3","scid":79375206,"m4ahash":"","privilege_128":0,"_is_recommend":0,"privilege_flac":0,"price_320":0,"trac":"","mvtype":0,"privilege_320":0,"pay_type_128":0,"mvhash":"","trans_param":{"cpy_grade":5,"musicpack_advance":0,"cpy_level":1,"cid":110003035,"hash_multitrack":"0179F91B2336E3E49C4E70BD2DDFAF18","pay_block_tpl":1,"classmap":{"attr0":100663304},"display_rate":0,"appid_block":"3124","display":0,"cpy_attr0":0},"privilege":8,"price_flac":0,"mv":"","album_audio_id":287273748,"all_privs":{"4":{"status":0,"privilege":5,"fail_process":0},"6":{"status":0,"privilege":5,"fail_process":0},"3":{"status":0,"privilege":5,"fail_process":0},"5":{"status":0,"privilege":5,"fail_process":0}},"vip":0,"type_flac":"","price_128":0,"hmvhash":"","hash":"3B0065C4CDC42FE406481B8BBC391F42","size":"4538406","ismvfilehead":0,"filesize_super":0,"musictrac":0,"old_cpy":0,"fail_process":4,"320size":"11345240","320time":"283000","fail_process_128":0,"320hash":"9829B0D146D9E96B2F252852F4401DB2","type":"audio","audio_id":79375206,"m4asize":0,"type_128":""},{"filesize_high":0,"hash_ape":"","pay_type_320":0,"hashflac":"47BA453C6D6891705101009F414DF57C","tracker_info":{},"topic_url":"","type_320":"","pkg_price_320":0,"sid":273784701,"topic_remark":"","filesize_ape":0,"bitrate":128,"isfilehead":100,"time":"224000","name":"Excision、Wooli、HALIENE - Erase You","pkg_price_flac":0,"pay_type_flac":0,"320isfilehead":100,"hash_super":"","hash_high":"","fail_process_flac":0,"fail_process_320":0,"pay_type":3,"pkg_price_128":0,"album_id":"39206779","publish":1,"filesize_flac":26888899,"ext":"mp3","scid":81856637,"m4ahash":"","privilege_128":0,"_is_recommend":0,"privilege_flac":0,"price_320":0,"trac":"","mvtype":0,"privilege_320":0,"pay_type_128":0,"mvhash":"","trans_param":{"cpy_grade":5,"musicpack_advance":0,"cpy_level":1,"cid":114430277,"hash_multitrack":"FBB43DCB752AF9BE11CB39EA08C385D2","pay_block_tpl":1,"classmap":{"attr0":100663304},"display_rate":0,"appid_block":"3124","display":0,"cpy_attr0":0},"privilege":8,"price_flac":0,"mv":"","album_audio_id":273784701,"all_privs":{"4":{"status":0,"privilege":5,"fail_process":0},"6":{"status":0,"privilege":5,"fail_process":0},"3":{"status":0,"privilege":5,"fail_process":0},"5":{"status":0,"privilege":5,"fail_process":0}},"vip":0,"type_flac":"","price_128":0,"hmvhash":"","hash":"393603434CCA68C0B882F4AA8531E55D","size":"3585119","ismvfilehead":0,"filesize_super":0,"musictrac":0,"old_cpy":0,"fail_process":4,"320size":"8962373","320time":"224000","fail_process_128":0,"320hash":"31D5E878E8AE9170D1A7BEE8E57BF085","type":"audio","audio_id":81856637,"m4asize":0,"type_128":""},{"filesize_high":0,"hash_ape":"","pay_type_320":0,"hashflac":"0243BAB7143FF53D3CB6C9C995BAE606","tracker_info":{},"topic_url":"","type_320":"","pkg_price_320":0,"sid":374054210,"topic_remark":"","filesize_ape":0,"bitrate":128,"isfilehead":100,"time":"188551","name":"花粥 - 晴天和猫","pkg_price_flac":0,"pay_type_flac":0,"320isfilehead":100,"hash_super":"","hash_high":"","fail_process_flac":0,"fail_process_320":0,"pay_type":3,"pkg_price_128":0,"album_id":"53390085","publish":1,"filesize_flac":20543368,"ext":"mp3","scid":145525360,"m4ahash":"","privilege_128":0,"_is_recommend":0,"privilege_flac":0,"price_320":0,"trac":"","mvtype":0,"privilege_320":0,"pay_type_128":0,"mvhash":"","trans_param":{"cpy_grade":5,"cpy_attr0":0,"cpy_level":1,"cid":195144728,"hash_multitrack":"3ED3FEE1392673D72C4C5645AB445C80","pay_block_tpl":1,"display_rate":0,"classmap":{"attr0":100663304},"display":0,"musicpack_advance":0},"privilege":8,"price_flac":0,"mv":"","album_audio_id":374054210,"all_privs":{"4":{"status":0,"privilege":5,"fail_process":0},"6":{"privilege":10,"status":0,"trans_param":{"cpy_grade":5,"musicpack_advance":0,"cpy_level":1,"identity_block":1,"pay_block_tpl":1,"cpy_attr0":0,"display_rate":0,"classmap":{"attr0":100663304},"display":0,"cid":195144728},"pay_type":1,"fail_process":4},"3":{"status":0,"privilege":5,"fail_process":0},"5":{"privilege":10,"status":0,"trans_param":{"cpy_grade":5,"musicpack_advance":0,"cpy_level":1,"identity_block":1,"pay_block_tpl":1,"cpy_attr0":0,"display_rate":0,"classmap":{"attr0":100663304},"display":0,"cid":195144728},"pay_type":1,"fail_process":4}},"vip":0,"type_flac":"","price_128":0,"hmvhash":"","hash":"8DC89C2A51680F679866F1E96384B9EE","size":"3017443","ismvfilehead":0,"filesize_super":0,"musictrac":0,"old_cpy":0,"fail_process":4,"320size":"7542822","320time":"188551","fail_process_128":0,"320hash":"81FA871F613091DC7B4E8F4D4BA1A624","type":"audio","audio_id":145525360,"m4asize":0,"type_128":""},{"filesize_high":0,"hash_ape":"","pay_type_320":0,"hashflac":"E6C4054227E684E59DBC9158200D64D9","tracker_info":{},"topic_url":"","type_320":"","pkg_price_320":0,"sid":195295615,"topic_remark":"","filesize_ape":0,"bitrate":128,"isfilehead":100,"time":"247000","name":"Lana Del Rey - Mariners Apartment Complex","pkg_price_flac":0,"pay_type_flac":0,"320isfilehead":100,"hash_super":"","hash_high":"","fail_process_flac":0,"fail_process_320":0,"pay_type":3,"pkg_price_128":0,"album_id":"27997633","publish":1,"filesize_flac":21833520,"ext":"mp3","scid":43337686,"m4ahash":"","privilege_128":0,"_is_recommend":0,"privilege_flac":0,"price_320":0,"trac":"","mvtype":0,"privilege_320":0,"pay_type_128":0,"mvhash":"","trans_param":{"cpy_grade":5,"musicpack_advance":0,"cpy_level":1,"cid":75132388,"hash_multitrack":"BD8F4F4A816E760091755DD82952BDE2","pay_block_tpl":1,"classmap":{"attr0":100663808},"display_rate":1,"appid_block":"2906,3124","display":4,"cpy_attr0":0},"privilege":8,"price_flac":0,"mv":"","album_audio_id":195295615,"all_privs":{"4":{"status":0,"privilege":5,"fail_process":0},"6":{"status":0,"privilege":5,"fail_process":0},"3":{"status":0,"privilege":5,"fail_process":0},"5":{"status":0,"privilege":5,"fail_process":0}},"vip":0,"type_flac":"","price_128":0,"hmvhash":"","hash":"88DDB19D8803E8066DB18D97427C4BE4","size":"3955887","ismvfilehead":0,"filesize_super":0,"musictrac":0,"old_cpy":0,"fail_process":4,"320size":"9889236","320time":"247000","fail_process_128":0,"320hash":"C757E8EF153B4AD80C9E735478F7C237","type":"audio","audio_id":43337686,"m4asize":0,"type_128":""},{"filesize_high":0,"hash_ape":"","pay_type_320":0,"hashflac":"","tracker_info":{},"topic_url":"","type_320":"","pkg_price_320":0,"sid":335564332,"topic_remark":"","filesize_ape":0,"bitrate":128,"isfilehead":100,"time":"194000","name":"Billie Eilish - Male Fantasy","pkg_price_flac":0,"pay_type_flac":0,"320isfilehead":100,"hash_super":"","hash_high":"","fail_process_flac":0,"fail_process_320":0,"pay_type":3,"pkg_price_128":0,"album_id":"48569893","publish":1,"filesize_flac":0,"ext":"mp3","scid":115277277,"m4ahash":"","privilege_128":0,"_is_recommend":0,"privilege_flac":0,"price_320":0,"trac":"","mvtype":0,"privilege_320":0,"pay_type_128":0,"mvhash":"","trans_param":{"cpy_grade":5,"musicpack_advance":0,"cpy_level":1,"cid":168064387,"hash_multitrack":"5E971B067FFAFB4EC8A0113943736BAA","pay_block_tpl":1,"classmap":{"attr0":100663304},"display_rate":0,"appid_block":"2906,3124","display":0,"cpy_attr0":0},"privilege":8,"price_flac":0,"mv":"","album_audio_id":335564332,"all_privs":{"4":{"status":0,"privilege":5,"fail_process":0},"6":{"status":0,"privilege":5,"fail_process":0},"3":{"status":0,"privilege":5,"fail_process":0},"5":{"status":0,"privilege":5,"fail_process":0}},"vip":0,"type_flac":"","price_128":0,"hmvhash":"","hash":"3C2A9A3247D7F367D68542934847ADC1","size":"3119497","ismvfilehead":0,"filesize_super":0,"musictrac":0,"old_cpy":0,"fail_process":4,"320size":"7798006","320time":"194000","fail_process_128":0,"320hash":"2163EB22C4E4335B99EBF765E2B4AC74","type":"audio","audio_id":115277277,"m4asize":0,"type_128":""},{"filesize_high":0,"hash_ape":"","pay_type_320":0,"hashflac":"9782061E7A91DA607D1378ACB5F897ED","tracker_info":{},"topic_url":"","type_320":"","pkg_price_320":0,"sid":67667621,"topic_remark":"","filesize_ape":0,"bitrate":128,"isfilehead":100,"time":"216000","name":"余佳运 - 情话","pkg_price_flac":0,"pay_type_flac":0,"320isfilehead":100,"hash_super":"","hash_high":"","fail_process_flac":0,"fail_process_320":0,"pay_type":3,"pkg_price_128":0,"album_id":"2883612","publish":1,"filesize_flac":18394052,"ext":"mp3","scid":27540752,"m4ahash":"","privilege_128":0,"_is_recommend":0,"privilege_flac":0,"price_320":0,"trac":"","mvtype":0,"privilege_320":0,"pay_type_128":0,"mvhash":"","trans_param":{"cpy_grade":5,"cpy_attr0":0,"cpy_level":1,"cid":22546341,"hash_multitrack":"F218249967DD5151A46153E906D3CA90","pay_block_tpl":1,"display_rate":0,"classmap":{"attr0":100663304},"display":0,"musicpack_advance":0},"privilege":8,"price_flac":0,"mv":"","album_audio_id":67667621,"all_privs":{"4":{"status":0,"privilege":8,"fail_process":4},"6":{"status":0,"privilege":8,"fail_process":4},"3":{"status":0,"privilege":8,"fail_process":4},"5":{"status":0,"privilege":8,"fail_process":4}},"vip":0,"type_flac":"","price_128":0,"hmvhash":"","hash":"95B78E4067303245396DEEB2E9467F81","size":"3464653","ismvfilehead":0,"filesize_super":0,"musictrac":0,"old_cpy":1,"fail_process":4,"320size":"8660876","320time":"216000","fail_process_128":0,"320hash":"40F672072B104345D8E7CC3A391BC1F3","type":"audio","audio_id":27540752,"m4asize":0,"type_128":""},{"filesize_high":0,"hash_ape":"","pay_type_320":0,"hashflac":"32E0D2B815E6407D45D0266FF756052D","tracker_info":{},"topic_url":"","type_320":"","pkg_price_320":0,"sid":160703639,"topic_remark":"","filesize_ape":0,"bitrate":128,"isfilehead":100,"time":"278000","name":"安来宁、赵宥乔 - 人来人往","pkg_price_flac":0,"pay_type_flac":0,"320isfilehead":100,"hash_super":"","hash_high":"","fail_process_flac":0,"fail_process_320":0,"pay_type":3,"pkg_price_128":0,"album_id":"22330937","publish":1,"filesize_flac":29847292,"ext":"mp3","scid":55619080,"m4ahash":"","privilege_128":0,"_is_recommend":0,"privilege_flac":0,"price_320":0,"trac":"","mvtype":0,"privilege_320":0,"pay_type_128":0,"mvhash":"","trans_param":{"cpy_grade":5,"cpy_attr0":0,"cpy_level":1,"cid":71630035,"hash_multitrack":"C5A132DBDA45C615B146E61BE9EC6706","pay_block_tpl":1,"display_rate":0,"classmap":{"attr0":100663304},"display":0,"musicpack_advance":0},"privilege":8,"price_flac":0,"mv":"","album_audio_id":160703639,"all_privs":{"4":{"status":0,"privilege":5,"fail_process":0},"6":{"status":0,"privilege":5,"fail_process":0},"3":{"status":0,"privilege":5,"fail_process":0},"5":{"status":0,"privilege":5,"fail_process":0}},"vip":0,"type_flac":"","price_128":0,"hmvhash":"","hash":"6557CC730D112E95345B8079CB8F2280","size":"4449001","ismvfilehead":0,"filesize_super":0,"musictrac":0,"old_cpy":0,"fail_process":4,"320size":"11122138","320time":"278000","fail_process_128":0,"320hash":"3E454A659CDA3CC5EA2B86FFA42956FF","type":"audio","audio_id":55619080,"m4asize":0,"type_128":""},{"filesize_high":0,"hash_ape":"","pay_type_320":0,"hashflac":"163FCCCF68E3F212571BFB2000580654","tracker_info":{},"topic_url":"","type_320":"","pkg_price_320":0,"sid":105985835,"topic_remark":"","filesize_ape":0,"bitrate":128,"isfilehead":100,"time":"251000","name":"打首獄門同好会 - 布団の中から出たくない","pkg_price_flac":0,"pay_type_flac":0,"320isfilehead":100,"hash_super":"","hash_high":"","fail_process_flac":0,"fail_process_320":0,"pay_type":3,"pkg_price_128":0,"album_id":"8321636","publish":1,"filesize_flac":28827721,"ext":"mp3","scid":36554056,"m4ahash":"","privilege_128":0,"_is_recommend":0,"privilege_flac":0,"price_320":0,"trac":"","mvtype":0,"privilege_320":0,"pay_type_128":0,"mvhash":"","trans_param":{"cpy_grade":5,"cpy_attr0":0,"cpy_level":1,"cid":85231470,"hash_multitrack":"4491D5CDDA80B7AAB371E9ABC5F681CE","pay_block_tpl":1,"display_rate":0,"classmap":{"attr0":100663304},"display":0,"musicpack_advance":0},"privilege":8,"price_flac":0,"mv":"","album_audio_id":105985835,"all_privs":{"4":{"status":0,"privilege":5,"fail_process":0},"6":{"status":0,"privilege":5,"fail_process":0},"3":{"status":0,"privilege":5,"fail_process":0},"5":{"status":0,"privilege":5,"fail_process":0}},"vip":0,"type_flac":"","price_128":0,"hmvhash":"","hash":"5A7F874CB97EBB08E0EA2CEDFC1652F2","size":"4026416","ismvfilehead":0,"filesize_super":0,"musictrac":0,"old_cpy":1,"fail_process":4,"320size":"10065718","320time":"251611","fail_process_128":0,"320hash":"4E54144AA2062AC62309ABBD47FB019E","type":"audio","audio_id":36554056,"m4asize":0,"type_128":""},{"filesize_high":0,"hash_ape":"","pay_type_320":0,"hashflac":"8B7CE6B78D46CB54656F1783A95B9E61","tracker_info":{},"topic_url":"","type_320":"","pkg_price_320":0,"sid":106708694,"topic_remark":"","filesize_ape":0,"bitrate":128,"isfilehead":100,"time":"186000","name":"XXXTENTACION - NUMB","pkg_price_flac":0,"pay_type_flac":0,"320isfilehead":100,"hash_super":"","hash_high":"","fail_process_flac":0,"fail_process_320":0,"pay_type":3,"pkg_price_128":0,"album_id":"8427890","publish":1,"filesize_flac":17161779,"ext":"mp3","scid":37384938,"m4ahash":"","privilege_128":0,"_is_recommend":0,"privilege_flac":0,"price_320":0,"trac":"","mvtype":0,"privilege_320":0,"pay_type_128":0,"mvhash":"","trans_param":{"cpy_grade":5,"musicpack_advance":0,"cpy_level":1,"cid":32475889,"hash_multitrack":"4A233ACE924BFB4CB053E2F17D8DB31B","pay_block_tpl":1,"classmap":{"attr0":100663304},"display_rate":0,"appid_block":"2906,3124","display":0,"cpy_attr0":0},"privilege":8,"price_flac":0,"mv":"","album_audio_id":106708694,"all_privs":{"4":{"status":0,"privilege":5,"fail_process":0},"6":{"status":0,"privilege":5,"fail_process":0},"3":{"status":0,"privilege":5,"fail_process":0},"5":{"status":0,"privilege":5,"fail_process":0}},"vip":0,"type_flac":"","price_128":0,"hmvhash":"","hash":"746746C06CA072F7E1FC481BFC88E0E0","size":"2981534","ismvfilehead":0,"filesize_super":0,"musictrac":0,"old_cpy":0,"fail_process":4,"320size":"7453489","320time":"186000","fail_process_128":0,"320hash":"FD6C708949E5781D1B4B4BFA3E1CBBA1","type":"audio","audio_id":37384938,"m4asize":0,"type_128":""},{"filesize_high":0,"hash_ape":"","pay_type_320":0,"hashflac":"4D6D0F6C594F7AECD7213336F5E9F45D","tracker_info":{},"topic_url":"","type_320":"","pkg_price_320":0,"sid":225171368,"topic_remark":"","filesize_ape":0,"bitrate":128,"isfilehead":100,"time":"102000","name":"xfruge - I Know You so Well","pkg_price_flac":0,"pay_type_flac":0,"320isfilehead":100,"hash_super":"","hash_high":"","fail_process_flac":0,"fail_process_320":0,"pay_type":3,"pkg_price_128":0,"album_id":"31539909","publish":1,"filesize_flac":6866154,"ext":"mp3","scid":61553525,"m4ahash":"","privilege_128":0,"_is_recommend":0,"privilege_flac":0,"price_320":0,"trac":"","mvtype":0,"privilege_320":0,"pay_type_128":0,"mvhash":"","trans_param":{"cpy_grade":5,"cpy_attr0":0,"cpy_level":1,"cid":78739320,"hash_multitrack":"C3583AB22E0AB3B6BDCD28650070EE6A","pay_block_tpl":1,"display_rate":0,"classmap":{"attr0":100663304},"display":0,"musicpack_advance":0},"privilege":8,"price_flac":0,"mv":"","album_audio_id":225171368,"all_privs":{"4":{"status":0,"privilege":5,"fail_process":0},"6":{"privilege":10,"status":0,"trans_param":{"cpy_grade":5,"musicpack_advance":0,"cpy_level":1,"identity_block":1,"pay_block_tpl":1,"cpy_attr0":0,"display_rate":0,"classmap":{"attr0":100663304},"display":0,"cid":78739320},"pay_type":1,"fail_process":4},"3":{"status":0,"privilege":5,"fail_process":0},"5":{"privilege":10,"status":0,"trans_param":{"cpy_grade":5,"musicpack_advance":0,"cpy_level":1,"identity_block":1,"pay_block_tpl":1,"cpy_attr0":0,"display_rate":0,"classmap":{"attr0":100663304},"display":0,"cid":78739320},"pay_type":1,"fail_process":4}},"vip":0,"type_flac":"","price_128":0,"hmvhash":"","hash":"A1329B2E3C064AB406FB4765B4AB8788","size":"1643257","ismvfilehead":0,"filesize_super":0,"musictrac":0,"old_cpy":0,"fail_process":4,"320size":"4107551","320time":"102661","fail_process_128":0,"320hash":"853B0198B93677E06E112D14CB97C248","type":"audio","audio_id":61553525,"m4asize":0,"type_128":""},{"filesize_high":0,"hash_ape":"","pay_type_320":0,"hashflac":"EFF1270477AE65EC1EA162D28C38C1C7","tracker_info":{},"topic_url":"","type_320":"","pkg_price_320":0,"sid":180908545,"topic_remark":"","filesize_ape":0,"bitrate":128,"isfilehead":100,"time":"270000","name":"欧阳娜娜、海龟先生 - 奇遇","pkg_price_flac":0,"pay_type_flac":0,"320isfilehead":100,"hash_super":"","hash_high":"","fail_process_flac":0,"fail_process_320":0,"pay_type":0,"pkg_price_128":0,"album_id":"26244214","publish":1,"filesize_flac":30960972,"ext":"mp3","scid":57545518,"m4ahash":"","privilege_128":0,"_is_recommend":0,"privilege_flac":0,"price_320":0,"trac":"","mvtype":0,"privilege_320":0,"pay_type_128":0,"mvhash":"","trans_param":{"cpy_grade":5,"cpy_attr0":0,"cpy_level":1,"cid":73940109,"hash_multitrack":"7F98240702CE498A751EF543EE6BD5D8","pay_block_tpl":1,"display_rate":1,"classmap":{"attr0":100667400},"display":32,"musicpack_advance":0},"privilege":0,"price_flac":0,"mv":"","album_audio_id":180908545,"all_privs":{"4":{"status":0,"privilege":5,"fail_process":0},"6":{"privilege":10,"status":0,"trans_param":{"cpy_grade":5,"musicpack_advance":0,"cpy_level":1,"identity_block":1,"pay_block_tpl":1,"cpy_attr0":0,"display_rate":1,"classmap":{"attr0":100667400},"display":32,"cid":73940109},"pay_type":1,"fail_process":4},"3":{"status":0,"privilege":5,"fail_process":0},"5":{"privilege":10,"status":0,"trans_param":{"cpy_grade":5,"musicpack_advance":0,"cpy_level":1,"identity_block":1,"pay_block_tpl":1,"cpy_attr0":0,"display_rate":1,"classmap":{"attr0":100667400},"display":32,"cid":73940109},"pay_type":1,"fail_process":4}},"vip":0,"type_flac":"","price_128":0,"hmvhash":"","hash":"30CBA2F909825541460D197A1DD098AE","size":"4312704","ismvfilehead":0,"filesize_super":0,"musictrac":0,"old_cpy":1,"fail_process":0,"320size":"10781459","320time":"270000","fail_process_128":0,"320hash":"8129496E6F514211B2645DACD8237DDE","type":"audio","audio_id":57545518,"m4asize":0,"type_128":""},{"filesize_high":0,"hash_ape":"","pay_type_320":0,"hashflac":"28CDCB0F042497AFDC2350189D3E83A0","tracker_info":{},"topic_url":"","type_320":"","pkg_price_320":0,"sid":286619463,"topic_remark":"","filesize_ape":0,"bitrate":128,"isfilehead":100,"time":"249000","name":"宋宇宁 - 被逼的浪子不回头","pkg_price_flac":0,"pay_type_flac":0,"320isfilehead":100,"hash_super":"","hash_high":"","fail_process_flac":0,"fail_process_320":0,"pay_type":3,"pkg_price_128":0,"album_id":"40992334","publish":1,"filesize_flac":30165256,"ext":"mp3","scid":89799116,"m4ahash":"","privilege_128":0,"_is_recommend":0,"privilege_flac":0,"price_320":0,"trac":"","mvtype":0,"privilege_320":0,"pay_type_128":0,"mvhash":"","trans_param":{"cpy_grade":5,"musicpack_advance":0,"cpy_level":1,"cid":129454876,"hash_multitrack":"693CD1694A46DCDE38045F45F6ECDF79","pay_block_tpl":1,"classmap":{"attr0":100663304},"display_rate":0,"appid_block":"3124","display":0,"cpy_attr0":0},"privilege":8,"price_flac":0,"mv":"","album_audio_id":286619463,"all_privs":{"4":{"status":0,"privilege":5,"fail_process":0},"6":{"privilege":10,"status":0,"trans_param":{"cpy_grade":5,"cpy_attr0":0,"cpy_level":1,"identity_block":1,"musicpack_advance":0,"pay_block_tpl":1,"classmap":{"attr0":100663304},"display_rate":0,"appid_block":"3124","display":0,"cid":129454876},"pay_type":1,"fail_process":4},"3":{"status":0,"privilege":5,"fail_process":0},"5":{"privilege":10,"status":0,"trans_param":{"cpy_grade":5,"cpy_attr0":0,"cpy_level":1,"identity_block":1,"musicpack_advance":0,"pay_block_tpl":1,"classmap":{"attr0":100663304},"display_rate":0,"appid_block":"3124","display":0,"cid":129454876},"pay_type":1,"fail_process":4}},"vip":0,"type_flac":"","price_128":0,"hmvhash":"","hash":"2DAB757D515E9AFE21B512B2CF818A39","size":"3996321","ismvfilehead":0,"filesize_super":0,"musictrac":0,"old_cpy":1,"fail_process":4,"320size":"9990483","320time":"249000","fail_process_128":0,"320hash":"AA831A4188FA4B1AD311C9CA1E469341","type":"audio","audio_id":89799116,"m4asize":0,"type_128":""},{"filesize_high":0,"hash_ape":"","pay_type_320":0,"hashflac":"CAF089FB549B0AED11395BB7DF46A374","tracker_info":{},"topic_url":"","type_320":"","pkg_price_320":0,"sid":127218401,"topic_remark":"","filesize_ape":0,"bitrate":128,"isfilehead":100,"time":"248000","name":"愚青 - 地球上最后一只萤火虫","pkg_price_flac":0,"pay_type_flac":0,"320isfilehead":100,"hash_super":"","hash_high":"","fail_process_flac":0,"fail_process_320":0,"pay_type":3,"pkg_price_128":0,"album_id":"14235261","publish":1,"filesize_flac":22646852,"ext":"mp3","scid":47397297,"m4ahash":"","privilege_128":0,"_is_recommend":0,"privilege_flac":0,"price_320":0,"trac":"","mvtype":0,"privilege_320":0,"pay_type_128":0,"mvhash":"","trans_param":{"cpy_grade":5,"cpy_attr0":0,"cpy_level":1,"cid":53352045,"hash_multitrack":"84A834A348BCAEF158F60D89CF737449","pay_block_tpl":1,"display_rate":0,"classmap":{"attr0":100663304},"display":0,"musicpack_advance":0},"privilege":8,"price_flac":0,"mv":"","album_audio_id":127218401,"all_privs":{"4":{"status":0,"privilege":5,"fail_process":0},"6":{"privilege":10,"status":0,"trans_param":{"cpy_grade":5,"musicpack_advance":0,"cpy_level":1,"identity_block":1,"pay_block_tpl":1,"cpy_attr0":0,"display_rate":0,"classmap":{"attr0":100663304},"display":0,"cid":53352045},"pay_type":1,"fail_process":4},"3":{"status":0,"privilege":5,"fail_process":0},"5":{"privilege":10,"status":0,"trans_param":{"cpy_grade":5,"musicpack_advance":0,"cpy_level":1,"identity_block":1,"pay_block_tpl":1,"cpy_attr0":0,"display_rate":0,"classmap":{"attr0":100663304},"display":0,"cid":53352045},"pay_type":1,"fail_process":4}},"vip":0,"type_flac":"","price_128":0,"hmvhash":"","hash":"9EE437E6259AF1BBB61A675209116028","size":"3968736","ismvfilehead":0,"filesize_super":0,"musictrac":0,"old_cpy":1,"fail_process":4,"320size":"9921520","320time":"248000","fail_process_128":0,"320hash":"2144A1C8C83CF277146F452903803E86","type":"audio","audio_id":47397297,"m4asize":0,"type_128":""},{"filesize_high":0,"hash_ape":"","pay_type_320":0,"hashflac":"C77CEB4B83B0662FC2489A9ADDAA2A60","tracker_info":{},"topic_url":"","type_320":"","pkg_price_320":0,"sid":237005920,"topic_remark":"","filesize_ape":0,"bitrate":128,"isfilehead":100,"time":"203467","name":"Woodes - This Is My Year","pkg_price_flac":0,"pay_type_flac":0,"320isfilehead":100,"hash_super":"","hash_high":"","fail_process_flac":0,"fail_process_320":0,"pay_type":3,"pkg_price_128":0,"album_id":"33895755","publish":1,"filesize_flac":21629736,"ext":"mp3","scid":63346363,"m4ahash":"","privilege_128":0,"_is_recommend":0,"privilege_flac":0,"price_320":0,"trac":"","mvtype":0,"privilege_320":0,"pay_type_128":0,"mvhash":"","trans_param":{"cpy_grade":5,"cpy_attr0":0,"cpy_level":1,"cid":81500182,"hash_multitrack":"D81FBBAC2D442DCBC4095C1C47DF8B10","pay_block_tpl":1,"display_rate":0,"classmap":{"attr0":100663304},"display":0,"musicpack_advance":0},"privilege":8,"price_flac":0,"mv":"","album_audio_id":237005920,"all_privs":{"4":{"status":0,"privilege":5,"fail_process":0},"6":{"status":0,"privilege":5,"fail_process":0},"3":{"status":0,"privilege":5,"fail_process":0},"5":{"status":0,"privilege":5,"fail_process":0}},"vip":0,"type_flac":"","price_128":0,"hmvhash":"","hash":"0BD7FF2A26FA4B649EE5FB542502B624","size":"3256150","ismvfilehead":0,"filesize_super":0,"musictrac":0,"old_cpy":1,"fail_process":4,"320size":"8140003","320time":"203000","fail_process_128":0,"320hash":"A2D6F4999F2B5C5E3E4E6C95084E5F82","type":"audio","audio_id":63346363,"m4asize":0,"type_128":""},{"filesize_high":0,"hash_ape":"","pay_type_320":0,"hashflac":"4F8947E76DF7410EB8CE7148603D410F","tracker_info":{},"topic_url":"","type_320":"","pkg_price_320":0,"sid":177902078,"topic_remark":"","filesize_ape":0,"bitrate":128,"isfilehead":100,"time":"275000","name":"YUNGBLUD - Time In A Bottle","pkg_price_flac":0,"pay_type_flac":0,"320isfilehead":100,"hash_super":"","hash_high":"","fail_process_flac":0,"fail_process_320":0,"pay_type":1,"pkg_price_128":0,"album_id":"25912867","publish":1,"filesize_flac":32503799,"ext":"mp3","scid":57334883,"m4ahash":"","privilege_128":0,"_is_recommend":0,"privilege_flac":0,"price_320":0,"trac":"","mvtype":0,"privilege_320":0,"pay_type_128":0,"mvhash":"","trans_param":{"cpy_grade":5,"musicpack_advance":0,"cpy_level":1,"cid":93265614,"hash_multitrack":"327B7F264E7709245DFC2E5924C59A01","pay_block_tpl":1,"classmap":{"attr0":100663304},"display_rate":0,"appid_block":"3124","display":0,"cpy_attr0":0},"privilege":8,"price_flac":0,"mv":"","album_audio_id":177902078,"all_privs":{"4":{"status":0,"privilege":5,"fail_process":0},"6":{"privilege":10,"status":0,"trans_param":{"cpy_grade":5,"cpy_attr0":0,"cpy_level":1,"identity_block":1,"musicpack_advance":0,"pay_block_tpl":1,"classmap":{"attr0":100663304},"display_rate":0,"appid_block":"3124","display":0,"cid":93265614},"pay_type":1,"fail_process":4},"3":{"status":0,"privilege":5,"fail_process":0},"5":{"privilege":10,"status":0,"trans_param":{"cpy_grade":5,"cpy_attr0":0,"cpy_level":1,"identity_block":1,"musicpack_advance":0,"pay_block_tpl":1,"classmap":{"attr0":100663304},"display_rate":0,"appid_block":"3124","display":0,"cid":93265614},"pay_type":1,"fail_process":4}},"vip":0,"type_flac":"","price_128":0,"hmvhash":"","hash":"739DBE5B97BAF0CF1DF40D631E0A5815","size":"4414461","ismvfilehead":0,"filesize_super":0,"musictrac":0,"old_cpy":0,"fail_process":4,"320size":"11035070","320time":"275000","fail_process_128":0,"320hash":"99C1F3853F494AE461537CA6C8E9C0FC","type":"audio","audio_id":57334883,"m4asize":0,"type_128":""}]}]}
