{"error_code":0,"data":{"offset":620,"songlist":[{"audio_info":{"duration_128":129933,"hash_128":"BCA70AFB3FD56429856E469C31B98572","filesize_128":2079689},"audio_name":"John Lennon Is My Jesus Christ","author_name":"Buzzard Buzzard Buzzard","privilege_play":{"privilege_128":8},"album_info":{"album_name":"John Lennon Is My Jesus Christ","album_id":36281274,"sizable_cover":"http:\/\/imge.kugou.com\/stdmusic\/{size}\/20200212\/20200212082512686840.jpg"},"album_audio_id":249601167},{"audio_info":{"duration_128":225000,"hash_128":"E3D6B5B547901D85DBDF3647D202EBEF","filesize_128":3610589},"audio_name":"Hell Froze Over","author_name":"Kodaline","privilege_play":{"privilege_128":8},"album_info":{"album_name":"Politics of Living","album_id":8916583,"sizable_cover":"http:\/\/imge.kugou.com\/stdmusic\/{size}\/20180719\/20180719183452288065.jpg"},"album_audio_id":115389375},{"audio_info":{"duration_128":231000,"hash_128":"22DFCD064B7D53E4123D8110B645FCA2","filesize_128":3696848},"audio_name":"Say Sue Me","author_name":"Say Sue Me","privilege_play":{"privilege_128":8},"album_info":{"album_name":"We`ve Sobered Up","album_id":35637554,"sizable_cover":"http:\/\/imge.kugou.com\/stdmusic\/{size}\/20200104\/20200104110106560360.jpg"},"album_audio_id":246243440},{"audio_info":{"duration_128":279000,"hash_128":"F00813581A01F88AA7F734C373931F31","filesize_128":4473675},"audio_name":"Rogue Unit","author_name":"Secret Circuit","privilege_play":{"privilege_128":8},"album_info":{"album_name":"Tactile Galactics","album_id":757116,"sizable_cover":"http:\/\/imge.kugou.com\/stdmusic\/{size}\/20150718\/20150718172130581918.jpg"},"album_audio_id":30201283},{"audio_info":{"duration_128":201000,"hash_128":"8A6D0385893C9077E106C0526939DB44","filesize_128":3217737},"audio_name":"Head Like a Haunted House","author_name":"Queens of the Stone Age","privilege_play":{"privilege_128":0},"album_info":{"album_name":"Villains","album_id":3633265,"sizable_cover":"http:\/\/imge.kugou.com\/stdmusic\/{size}\/20170812\/20170812063009698923.jpg"},"album_audio_id":81498421},{"audio_info":{"duration_128":202000,"hash_128":"8F1CF34C6269565B050BA5CF37CD37FC","filesize_128":3232867},"audio_name":"Modern Job","author_name":"Sprints","privilege_play":{"privilege_128":8},"album_info":{"album_name":"Modern Job","album_id":49426158,"sizable_cover":"http:\/\/imge.kugou.com\/stdmusic\/{size}\/20211010\/20211010093803652661.jpg"},"album_audio_id":342028646},{"audio_info":{"duration_128":174000,"hash_128":"E8B2E3279E82EFC21C90A2F7B1F54D68","filesize_128":2777204},"audio_name":"If I Am Only My Thoughts","author_name":"Loving","privilege_play":{"privilege_128":8},"album_info":{"album_name":"If I Am Only My Thoughts","album_id":33086778,"sizable_cover":"http:\/\/imge.kugou.com\/stdmusic\/{size}\/20191109\/20191109023305535053.jpg"},"album_audio_id":232460190},{"audio_info":{"duration_128":184685,"hash_128":"48327326ECB7E393413FBDFC43AC8EAD","filesize_128":2955629},"audio_name":"Poster Boy (Explicit)","author_name":"Jane Holiday","privilege_play":{"privilege_128":8},"album_info":{"album_name":"Poster Boy","album_id":21240149,"sizable_cover":"http:\/\/imge.kugou.com\/stdmusic\/{size}\/20190523\/20190523063215156687.jpg"},"album_audio_id":156074839},{"audio_info":{"duration_128":177000,"hash_128":"22023E131690DC61713D645C05F31905","filesize_128":2833187},"audio_name":"Down N Out (Explicit)","author_name":"dying in designer","privilege_play":{"privilege_128":8},"album_info":{"album_name":"Nobody's Happy.","album_id":26693528,"sizable_cover":"http:\/\/imge.kugou.com\/stdmusic\/{size}\/20190811\/20190811221404403252.jpg"},"album_audio_id":184820811},{"audio_info":{"duration_128":204000,"hash_128":"9CE398CE36E56C6C58653F749338AAD3","filesize_128":3277490},"audio_name":"Any Day Will Be Fine","author_name":"Mojave 3","privilege_play":{"privilege_128":0},"album_info":{"album_name":"Any Day Will Be Fine","album_id":1591541,"sizable_cover":"http:\/\/imge.kugou.com\/stdmusic\/{size}\/20150718\/20150718060053491931.jpg"},"album_audio_id":38194718},{"audio_info":{"duration_128":118543,"hash_128":"7260BE0134CDA5565FEEDF84A165AAF5","filesize_128":1897332},"audio_name":"Best Day","author_name":"Dala","privilege_play":{"privilege_128":8},"album_info":{"album_name":"Best Day","album_id":564256,"sizable_cover":"http:\/\/imge.kugou.com\/stdmusic\/{size}\/20150719\/20150719052217490704.jpg"},"album_audio_id":28221532},{"audio_info":{"duration_128":151000,"hash_128":"86AF59F3D15F90D29AB2F46DD436F232","filesize_128":2430636},"audio_name":"OK","author_name":"Honey Hahs","privilege_play":{"privilege_128":0},"album_info":{"album_name":"OK","album_id":2781426,"sizable_cover":"http:\/\/imge.kugou.com\/stdmusic\/{size}\/20170707\/20170707001109290535.jpg"},"album_audio_id":66753391},{"audio_info":{"duration_128":185000,"hash_128":"419997745D5F02A443B52954C18DCE85","filesize_128":2976555},"audio_name":"All For Nothing","author_name":"Matt Berninger","privilege_play":{"privilege_128":8},"album_info":{"album_name":"Serpentine Prison","album_id":39597442,"sizable_cover":"http:\/\/imge.kugou.com\/stdmusic\/{size}\/20201016\/20201016091002442088.jpg"},"album_audio_id":277393392},{"audio_info":{"duration_128":242000,"hash_128":"FA0D75A20E2BC5A20401F63F0894DB3A","filesize_128":3886004},"audio_name":"Foolish Games","author_name":"Jewel","privilege_play":{"privilege_128":8},"album_info":{"album_name":"Greatest Hits","album_id":959196,"sizable_cover":"http:\/\/imge.kugou.com\/stdmusic\/{size}\/20210802\/20210802182502264374.jpg"},"album_audio_id":32031959},{"audio_info":{"duration_128":319000,"hash_128":"8BCDFC2F9FE8C8FD12D925CEB83E5AC4","filesize_128":5109809},"audio_name":"Follow Me Around","author_name":"Radiohead","privilege_play":{"privilege_128":0},"album_info":{"album_name":"Follow Me Around","album_id":49798077,"sizable_cover":"http:\/\/imge.kugou.com\/stdmusic\/{size}\/20211025\/20211025001704197662.jpg"},"album_audio_id":344824772},{"audio_info":{"duration_128":171000,"hash_128":"0A09960884CC4D2B3771CB326E91F5FC","filesize_128":2738730},"audio_name":"Escalators","author_name":"Midnight Sister","privilege_play":{"privilege_128":8},"album_info":{"album_name":"Painting the Roses","album_id":39469766,"sizable_cover":"http:\/\/imge.kugou.com\/stdmusic\/{size}\/20201004\/20201004205917217688.jpg"},"album_audio_id":276258825},{"audio_info":{"duration_128":261616,"hash_128":"18898AB3918B903BFB211276194076DD","filesize_128":4186278},"audio_name":"Magazine","author_name":"Joshua James","privilege_play":{"privilege_128":8},"album_info":{"album_name":"Build Me This","album_id":2527818,"sizable_cover":"http:\/\/imge.kugou.com\/stdmusic\/{size}\/20160908\/20160908062025676698.jpg"},"album_audio_id":63586757},{"audio_info":{"duration_128":184894,"hash_128":"9ED12C9C82A2D07D2797C17BF51C6CBB","filesize_128":2958999},"audio_name":"So I Can See You","author_name":"TONE、Coby Sey","privilege_play":{"privilege_128":8},"album_info":{"album_name":"So I Can See You","album_id":51043965,"sizable_cover":"http:\/\/imge.kugou.com\/stdmusic\/{size}\/20211210\/20211210075202570727.jpg"},"album_audio_id":357275897},{"audio_info":{"duration_128":316264,"hash_128":"F7F019F6AD1F5267F6A3D096D6F813C1","filesize_128":5060724},"audio_name":"Minus Sixty One","author_name":"Woodkid","privilege_play":{"privilege_128":8},"album_info":{"album_name":"S16","album_id":39594160,"sizable_cover":"http:\/\/imge.kugou.com\/stdmusic\/{size}\/20201016\/20201016092103517897.jpg"},"album_audio_id":277393547},{"audio_info":{"duration_128":288966,"hash_128":"898F7A275735F703ABE2793683130190","filesize_128":4624154},"audio_name":"It Hurt So Bad (第42届格莱美提名歌曲)","author_name":"Susan Tedeschi","privilege_play":{"privilege_128":8},"album_info":{"album_name":"2000 GRAMMY Nominees (格莱美的喝彩 2000)","album_id":1582339,"sizable_cover":"http:\/\/imge.kugou.com\/stdmusic\/{size}\/20160908\/20160908031721684437.jpg"},"album_audio_id":38081928}]},"status":1}
