{"error_code":0,"data":{"offset":320,"songlist":[{"audio_info":{"duration_128":232000,"hash_128":"C16F0C458570635509C06D03ECF40484","filesize_128":3713803},"audio_name":"Paperwalls","author_name":"Andreya Triana","privilege_play":{"privilege_128":8},"album_info":{"album_name":"Giants","album_id":699199,"sizable_cover":"http:\/\/imge.kugou.com\/stdmusic\/{size}\/20150716\/20150716023821548253.jpg"},"album_audio_id":29653567},{"audio_info":{"duration_128":306991,"hash_128":"A82F08CC677CFB7B215C0173C973EF33","filesize_128":4912564},"audio_name":"In This Moment","author_name":"Ryan Farish","privilege_play":{"privilege_128":8},"album_info":{"album_name":"Legacy - Greatest Hits 2000-2010","album_id":36343289,"sizable_cover":"http:\/\/imge.kugou.com\/stdmusic\/{size}\/20200218\/20200218204624384396.jpg"},"album_audio_id":249914312},{"audio_info":{"duration_128":202396,"hash_128":"F593334EFF6C1E4FDA2315EED6DC00AC","filesize_128":3239045},"audio_name":"Our Falling Snow","author_name":"Sleep Party People","privilege_play":{"privilege_128":8},"album_info":{"album_name":"Sleep Party People","album_id":629839,"sizable_cover":"http:\/\/imge.kugou.com\/stdmusic\/{size}\/20150719\/20150719031202465748.jpg"},"album_audio_id":28956217},{"audio_info":{"duration_128":296855,"hash_128":"0B44BA98B51262EC69AA5E8E37CE3DD0","filesize_128":4750324},"audio_name":"Surface","author_name":"Recondite","privilege_play":{"privilege_128":8},"album_info":{"album_name":"Dwell","album_id":33325323,"sizable_cover":"http:\/\/imge.kugou.com\/stdmusic\/{size}\/20191112\/20191112193505545828.jpg"},"album_audio_id":233912685},{"audio_info":{"duration_128":360000,"hash_128":"58719B50D3878919801FF4D669232DAC","filesize_128":5762217},"audio_name":"Fragments","author_name":"Sappheiros","privilege_play":{"privilege_128":8},"album_info":{"album_name":"Fragments","album_id":4041986,"sizable_cover":"http:\/\/imge.kugou.com\/stdmusic\/{size}\/20161028\/20161028131812571756.jpg"},"album_audio_id":88259797},{"audio_info":{"duration_128":196086,"hash_128":"9E1CD054C147A0F572F2E10C7BC90D07","filesize_128":3150464},"audio_name":"Choral Karma","author_name":"Ambitus","privilege_play":{"privilege_128":8},"album_info":{"album_name":"The BR Space Night Presents: Waternight Vol. 1","album_id":12550127,"sizable_cover":"http:\/\/imge.kugou.com\/stdmusic\/{size}\/20181116\/20181116193605351566.jpg"},"album_audio_id":122023733},{"audio_info":{"duration_128":288000,"hash_128":"FABB445D038B6DC8756AE327E4B025DA","filesize_128":4608742},"audio_name":"Cottons of Inertia","author_name":"General Elektriks","privilege_play":{"privilege_128":8},"album_info":{"album_name":"Good City for Dreamers (Deluxe Edition)","album_id":27985429,"sizable_cover":"http:\/\/imge.kugou.com\/stdmusic\/{size}\/20181118\/20181118115222502962.jpg"},"album_audio_id":195190270},{"audio_info":{"duration_128":256000,"hash_128":"A3E32364A26E149B2A4E08D06A21B959","filesize_128":4110900},"audio_name":"The Hitman for Hire (Explicit)","author_name":"DJ KING ASSASSIN","privilege_play":{"privilege_128":8},"album_info":{"album_name":"Hitman 4 Hire","album_id":35396850,"sizable_cover":"http:\/\/imge.kugou.com\/stdmusic\/{size}\/20191221\/20191221114815888612.jpg"},"album_audio_id":244854693},{"audio_info":{"duration_128":268000,"hash_128":"DEE15DDA6BE34BB1F547516876EE1454","filesize_128":4289397},"audio_name":"Funky In The Middle","author_name":"NickodemusJay Rodriguez、Ticklah","privilege_play":{"privilege_128":8},"album_info":{"album_name":"Endangered Species (Bonus Edition)","album_id":680644,"sizable_cover":"http:\/\/imge.kugou.com\/stdmusic\/{size}\/20190304\/20190304155207344409.jpg"},"album_audio_id":29471931},{"audio_info":{"duration_128":360000,"hash_128":"E31505E1E388B49455BCEB8FB16DC333","filesize_128":5764733},"audio_name":"CIRCLONT6A (141.98 syrobonkus mix 141.98 syrobonkus mix 141.98 syrobonkus mix 141.98 syrobonkus mix)","author_name":"Aphex Twin","privilege_play":{"privilege_128":8},"album_info":{"album_name":"SYRO","album_id":592675,"sizable_cover":"http:\/\/imge.kugou.com\/stdmusic\/{size}\/20150720\/20150720192253531497.jpg"},"album_audio_id":28562393},{"audio_info":{"duration_128":256026,"hash_128":"490ABA7B4450A7A27074A432027D8FB6","filesize_128":4097091},"audio_name":"Maybes","author_name":"Giraffage、Japanese Breakfast","privilege_play":{"privilege_128":8},"album_info":{"album_name":"Maybes","album_id":4080496,"sizable_cover":"http:\/\/imge.kugou.com\/stdmusic\/{size}\/20170930\/20170930114845183441.jpg"},"album_audio_id":89007703},{"audio_info":{"duration_128":250000,"hash_128":"9943D6DE82278DD32534FFB9AFE0AA25","filesize_128":4007650},"audio_name":"Tríptico(Frikstailers Remix) (Remix)","author_name":"Gotan Project","privilege_play":{"privilege_128":8},"album_info":{"album_name":"Club Secreto, Vol. 2","album_id":8137634,"sizable_cover":"http:\/\/imge.kugou.com\/stdmusic\/{size}\/20171217\/20171217172750285300.jpg"},"album_audio_id":104906243},{"audio_info":{"duration_128":196310,"hash_128":"DFEE01C0EA39FCF4191AA2DF97EAC022","filesize_128":3141615},"audio_name":"Fool","author_name":"Hungry Lucy","privilege_play":{"privilege_128":8},"album_info":{"album_name":"To Kill a King","album_id":645885,"sizable_cover":"http:\/\/imge.kugou.com\/stdmusic\/{size}\/20160908\/20160908022845518093.jpg"},"album_audio_id":29127168},{"audio_info":{"duration_128":302000,"hash_128":"2B159F3BE7016AC9FC000F1D34E34C9D","filesize_128":4844880},"audio_name":"Violet Colors (OriginalMix)","author_name":"Marga Sol","privilege_play":{"privilege_128":8},"album_info":{"album_name":"Chillout Orange, Vol. 7: Relaxing Chillout Vibes","album_id":49136179,"sizable_cover":"http:\/\/imge.kugou.com\/stdmusic\/{size}\/20210928\/20210928021216102576.jpg"},"album_audio_id":340026156},{"audio_info":{"duration_128":296000,"hash_128":"963939830B136A4377073BC8402204F1","filesize_128":4748728},"audio_name":"Santa María (Del buen ayre)","author_name":"Gotan Project","privilege_play":{"privilege_128":8},"album_info":{"album_name":"Live","album_id":1014077,"sizable_cover":"http:\/\/imge.kugou.com\/stdmusic\/{size}\/20160908\/20160908070050139222.jpg"},"album_audio_id":32651635},{"audio_info":{"duration_128":108669,"hash_128":"7146829DECB119B9217F48152CCCB4A6","filesize_128":1739432},"audio_name":"Sleepless","author_name":"Flume、Twin Shadow、Jezzabell Doran","privilege_play":{"privilege_128":8},"album_info":{"album_name":"Flume (Deluxe Edition)","album_id":14332928,"sizable_cover":"http:\/\/imge.kugou.com\/stdmusic\/{size}\/20190102\/20190102200330219382.jpg"},"album_audio_id":127538168},{"audio_info":{"duration_128":280000,"hash_128":"B29073777AA87BA8F27A7518E2DB032A","filesize_128":4487837},"audio_name":"CARONTE","author_name":"Apparat","privilege_play":{"privilege_128":8},"album_info":{"album_name":"LP5","album_id":19230917,"sizable_cover":"http:\/\/imge.kugou.com\/stdmusic\/{size}\/20190418\/20190418162310765227.jpg"},"album_audio_id":146071966},{"audio_info":{"duration_128":242000,"hash_128":"D2670FBCB24E16A446839120D39DEF58","filesize_128":3880555},"audio_name":"Rat Pack","author_name":"De Phazz","privilege_play":{"privilege_128":8},"album_info":{"album_name":"Lala 2.0 (Bonus Edition)","album_id":2450118,"sizable_cover":"http:\/\/imge.kugou.com\/stdmusic\/{size}\/20160907\/20160907194743363084.jpg"},"album_audio_id":62653243},{"audio_info":{"duration_128":294000,"hash_128":"7354DA4843BEAFF2841EB73EE3E6CD76","filesize_128":4712819},"audio_name":"I'm Raving","author_name":"Jan Delay、Moonbootica","privilege_play":{"privilege_128":8},"album_info":{"album_name":"Jumping All over the World - Whatever You Want","album_id":37176364,"sizable_cover":"http:\/\/imge.kugou.com\/stdmusic\/{size}\/20200419\/20200419093903246550.jpg"},"album_audio_id":254249854},{"audio_info":{"duration_128":244000,"hash_128":"B8526D97AA835F74783231FD2C3EB1EA","filesize_128":3917813},"audio_name":"Tiny Reminder No.1 (C-Pij Vocal)","author_name":"Two Lone Swordsmen","privilege_play":{"privilege_128":8},"album_info":{"album_name":"Further Reminders","album_id":952568,"sizable_cover":"http:\/\/imge.kugou.com\/stdmusic\/{size}\/20200812\/20200812174424149541.jpg"},"album_audio_id":31969961}]},"status":1}
